Workbook

Sheet Prospek 2026
B1: Prospek 2026 | C1: =SUM(C3:C90) -> 508090506620
A2: No | B2: Project Name | C2: Value excl. PPN | D2: Status | F2: CUSTOMER | G2: Desc | H2: Factory Promise | I2: Remarks Kontraktor | J2: Remarks Principle | K2: Remarks AI | L2: INSULATOR | M2: Remarks | N2: PIC | O2: Keterangan
A3: 1 | B3: PENGADAAN DAN PEMASANGAN INFRASTRUKTUR SISTEM PENGAMANAN DI WILAYAH UPT SEMARANG | C3: 5287458300 | K3: bidbiond pertama 8 jan - 6 jun ke-2 7 jun - 3 nov ke-3 3 nov - 2 april
A4: 2 | B4: Penggantian Earthwire SUTET 500kV Kembangan - Gandul Menjadi OPGW | C4: 8547877000
A5: 3 | B5: Penggantian Trafo ke 2 GI Cepu, dan Trafo ke 2 GI blora | C5: 11000000000 | K5: Terder Terbatas, 540 Hari Kerja, okt 2027
A6: 4 | B6: Perkuatan Sistem Proteksi Petir di Wilayah UPT Semarang | C6: 8600000000 | K6: Terder Terbatas, 260 Hari Kerja, okt 2026
A7: 5 | B7: Penggantian Earthwire Korosif di Wilayah UPT Semarang | C7: 16000000000 | K7: Tender Terbatas, 365 Hari Kerja, Maret 2027
A8: 6 | B8: Pengadaan dan Pemasangan V Insulator Akibat Andongan Rendah | C8: 13200000000 | K8: Tender Terbatas, 540 Hari Kerja, Sep 2027
A9: 7 | B9: Pengadaan dan Penggantian Sistem Proteksi di Wilayah UPT Semarang | C9: 4500000000 | K9: Tender Terbatas, 540 Hari Kerja, Sep 2027
A10: 8 | B10: Penanganan Anomali Midspan Joint Tersebar di Wilayah UPT Semarang | C10: 4700000000 | K10: Tender Terbatas, 365 Hari Kerja, April 2027
A11: 9 | B11: Penggantian CDE Tj Jati - Sayung | C11: 5700000000 | K11: Terder Terbatas, 365 Hari Kerja, April 2027
A12: 10 | B12: Penggantian Kabel Power dan Sealing End di GIS 150 kV Tambaklorok | C12: 24000000000 | K12: Terder Terbatas, 365 Hari Kerja, April 2027
A13: 11 | B13: Pengadaan Material OLTC GITET 500 kV Ungaran | C13: 6300000000 | K13: Terder Terbatas, 365 Hari Kerja, April 2027
A14: 12 | B14: Pengadaan Material Bushing 70kV | C14: 184000000 | K14: PL
A15: 13 | B15: Pengadaan Thermovisi | C15: 866000000 | K15: Terder Terbuka, 365 Hari Kerja, April 2027
A16: 14 | B16: Pengadaan Alat Uji Kadar Air dan PDKB | C16: 2800000000 | K16: Terder Terbuka, 365 Hari Kerja, Mei 2027
... A45: 43 | B45: Grounding UPT Bogor | C45: 5000000000 | K45: Terder Terbuka
A46: 44 | B46: PENGADAAN BARANG DAN JASA KONSTRUKSI SUTT 150 KV PEMECUTAN KELOD -TX. PESANGGARAN -TX. BANDARA / NUSA DUA (SECTION SUTT 150 KV TX. PESANGGARAN - NUSA DUA 1 -2 | C46: 3376418010 | F46: KSO PT. JAMPA INDOTAMA - PT. ALHAS JAYA GROUP
A47: 45 | B47: PENGADAAN BARANG DAN JASA KONSTRUKSI SUTT 150KV PEMECUTAN KELOD - TX. PENSANGGARAN - TX. BANDARA / NUSA DUA (SECTION SUTT 150KV PEMECUTAN KELOD (TX. PESANGGARAN) - TX. BANDARA DAN SUTT 150 KV PESANGGARAN - TX. BANDARA) | C47: 4500000000 | F47: PT GRIDTECH INDONESIA
C48: =SUM(C3:C47) -> 254045253310

Sheet Prospek 2025
B1: Prospek 2025 | C1: =SUM(C3:C86) -> 106686480886
A2: No | B2: Project Name | C2: Value excl. PPN | D2: Status | F2: CUSTOMER | G2: Desc | H2: Factory Promise | I2: Remarks Kontraktor | J2: Remarks Principle | K2: Remarks AI | L2: INSULATOR | M2: Remarks | N2: PIC | O2: Keterangan
A3: 1 | B3: Pengadaan Isolator Tersebar di UPK Bangka Belitung | C3: 975424000 | F3: Indodaya Naratama Abadi | K3: sdh ttd kontrak berlaku sampai 17 September, perpanjang jampel 180 hari sampai tgl 22 Feb 2026, surat jalan sudah tanggal 09/12, BA sudah dikerjakan, info pencairan Februari, BAP belum infonya di Februari
A4: 2 | B4: PEKERJAAN PEMBANGUNAN GITET 275/150 KV WOTU EXTENSION | C4: =479141500+361307000 -> 840448500 | F4: Kelinci Mas Unggul | K4: FU ke Emmy bagian tender ke pak syuaib bagian project belum ada update, pengumuman pememang tgl 29/09/25, stringset dan connector pakai material stock dari projek Wotu sebelumnya, perlu diagendakan ke KMU Makassar
A5: 3 | B5: PEMBANGUNAN TRANSMISI 150 KV PAKNING- SIAK: LOT 1&2 | C5: =D5 -> 14966403554 | D5: =5682983898+9283419656 -> 14966403554 | E5: Sumatra BAP Percie, NPC, Multifab,Citramas, Bukaka dan Twink | F5: Sapta Guna Utama PT, Berca Buana Sakti PT | I5: penjelasan 3 Agustus 2023, closing 13 September 2023 | K5: kita sdh supprt Closing 23 Des (diundur 21 Jan 25), mereka pakai hogn dan KAK LOT1&2 harga kita sudah paling murah mbak laely di Pantau lagi April 28, mundur 12/01 | N5: Marul
A6: 4 | B6: PEMBANGUNAN TRANSMISI 150 KV TANAH GROGOT - SEI DURIAN LOT: 1&2 | C6: =8830659545+9025675355 -> 17856334900 | D6: 6933786700 | E6: Kalimantan BAP NPC,citramas (tdk ikut), Citicon, WST, Twink, Citac, Tinakana | F6: Distraco, PT, PT. Citicon Adhinugraha | I6: penjelasan 2 Agustus 2023, closing 14 September 2023 | K6: Closing 19 Maret sdh diberikan penawaran, masih menunggu update, Closing 29 des, SGU Citicon, Distraco, mundur 12/01 | N6: Laely
A7: 5 | B7: PEMBANGUNAN TRANSMISI 150 KV SEI DURIAN - TARJUN LOT: 1&2 | C7: =8365887990+8550639810 -> 16916527800 | E7: BAP Distraco, Citicon, Bukaka, Multifab, Sangkan | F7: PT. Nusantara Power Construction, PT. Citicon Adhinugraha | K7: Closing 19 Maret sdh diberikan penawaran, masih menunggu update, Closing 29 des, SGU Citicon, Distraco, mundur 12/01 | N7: Laely
A8: 6 | B8: UPRATING TRAFO 1 GI 150 KV BUMI SEMARANG BARU | D8: 9600000000 | E8: 1. 9.672.721.037,00 (HPS), 2. tgl kontrak 21 Oktober 2024 semua material percepatan sdh clear, material yg lain di PO tgl 30 des kecuali MK, GS, CCTV, menunggu approval dwg dan WP, | F8: KSO KSCM - INA | J8: garansi material: ERI sdh ada namun scan aslinya ngambil di cikarang (x), Enindo blm ada (x), KMI baru cek draft (x), Putra nata asli (v), amptron asli (v) GTS Panel (x) | K8: kontrak sampai 29 november 2025 pemeliharaan 6 bulan sampai 30 mei 2026 , VIP termin 3 sudah dibayar 24/11, pending item: pekerjaan DFR dan AVR akan dilaksanakan di masa pemeliharaan,
A9: 7 | B9: PENGADAAN DAN PENGGANTIAN ISOLATOR DI UIT JBM | C9: 4247984850 | D9: Menunggu harga ACCC dari PLP berikut diskon finalnya | F9: PT KENCANA ALAM PUTRA | K9: SOA tgl 21 November minta list mana yang urgent terlebih dahulu sdh dikirim, sudah FAT, pengambilan parsial I tgl 2 okt ada permintaan list material selesai di 20 okt, pengambilan parsial ke-II di tgl 24 okt, parsial ke-III sudah diambil tanggal 26, kekurangannya est tgl 20/12 poin C item 1-15, poin D item 1-3, poin E 1-12, poin F item 1, poin G item 1, poin H item 1, poin I item 1-2, paling lama 21/03/2026, kalau pakai jalur udara lebih cepat 1 bulan bayar 15 juta, info dari PLP akan mengirim item yang sudah selesai
A10: 8 | B10: REVITALISASI GIS DI UNIT INDUK TRANSMISI JAWA BAGIAN TIMUR DAN BALI (OVERHAUL GIS SAWAHAN | C10: 372000000 | F10: PT. High Volt Technology | K10: DP sudah dibayar tgl 27 sept SOA Connector 27 okt material connector sudah digudang ugc tgl 29/10 menunggu pengambilan, SOA Insulator July 2026, insulator sdh di PO ulang ke PLP SOA (1 Juni)
A11: 9 | B11: PENGADAAN DAN PEMASANGAN INFRASTRUKTUR SISTEM PENGAMANAN DI WILAYAH UPT SEMARANG | D11: 5287458300 | E11: pinjam MASATEK note di isian kualifikasi minta situlis subcon indodaya | F11: PT. Indodaya Naratama Abadi | K11: bidbiond pertama 8 jan - 6 jun ke-2 7 jun - 3 nov ke-3 3 nov - 2 april
A12: 10 | B12: UPRATING 2 DIAMETER DI GISTET SURALAYA ARAH CILEGON | C12: 303313050 | F12: KSO PT. Kencana Alam Putra - Enindo Orbitama | K12: SOA 26 November, material di gudang Alam diambil Januari, 05/01 FU ke pak Eko
B13: PROJEK SURALAYA PENGGANTIAN TENSION DEAD END | C13: 35766810 | F13: PT. High Volt Technology | K13: dibayar tanggal 5/12, diambil Januari
A14: 12 | B14: PENGADAAN STRINGSET PROJECT WK ROKAN PAKET -A | C14: 227069038 | F14: PT. PLN Nusantara Power Construction | K14: revisi invoice sudah dikirim, material sudah masuk ke gudang tgl 27/11, kekurangan BA sudah dikirim tanggal 11/12, 05/01 FU ke Pak Irwan
A15: 14 | B15: PENGGANTIAN TRAFO #3 150/20 KV 60 MVA GI CENGKARENG DALAM RANGKA PENGGANTIAN TRAFO KONDISI BURUK DI UPT DURIKOSAMBI | C15: 20211800 | F15: PT Indevco Global | K15: indevco menang, menunggu pembayaran post insulator, invoice dikirim tgl 23/12
A16: 15 | B16: PENGGANTIAN CT 500 KV P0 DI WILAYAH UPT BEKASI | C16: 147385728 | F16: Duta Cakrawala indonesia, PT | K16: Menang, Baru ttd kontrak, Belum ada jadwal nanti diinfokan kemajuan time line, segara rilis PO dan akan dikabari, selain pakai PLP pakai KAK, sedang proses approval minggu ini, kontrak panjang menunggu CT belum dirilis PO masih dalam proses, info dari pak Hary belum. Planing Pekerjaan, menunggu CT On site FU 14 nov, sudah bertemu pak Hari 17/12
A17: 16 | B17: PEKERJAAN PEMBANGUNAN GI 150 KV SEBUKU NEW 30 MVA | C17: 969108200 | F17: PT PLN NUSANTARA POWER CONSTRUCTION, | K17: NPC MENANG, qty nya berkurang 70%, sudah kirim quote terbaru ke NPC,
A18: 17 | B18: PENYELESAIAN PENDING ITEM GI DAN TRANSMISI DALAM RANGKA STOP/STAP/STP PROYEK WILAYAH UPP JBT 4 | C18: 833387400 | F18: PT, Pas Jaya Mandiri | K18: Closing 25 Mei, PJM sdh menang, (Section 1 Amsak), (Section 2 Multifab), (Section 3 Citacontract), kontrak akhir menunggu update harga PLP,sdh approved sdng disiapkan kebuuthan materialnya apa saja UIP FU terakhir 01/12 ke pak Albert Markus menunggu BOQ dari PLN
A19: 18 | B19: PEMBANGUNAN GI 150 KV KTT INDORAMA BESERTA SUTT 150 KV KTT INDORAMA – INC (PADALARANG – JATILUHUR) | C19: 2337683607 | F19: PT. MULTI FABRINDO GEMILANG | K19: GI menggunakan KAK, menunggu diskon dari PLP 22/12, menunggu harga diskon dari Alam, terakhir upload di eproc multifab tanggal 31/12, request diskon ke PLP 27%, request diskon ke DEM 10%
A20: 19 | B20: PENGADAAN DAN PEMASANGAN MTU PO DI UIT JBB LINGKUP JASA PEMASANGAN MTU PO DI UPT CIKUPA | C20: 99450000 | F20: PT. Garda Perdana Security | K20: menang, sudah ttd kontrak, sedang kick of meeting, info rencana survey di bulan desember, jeko FU 12/12 sedang proses survey, FU 18/12 tidak ada respon, dijadwalkan silaturahmi w2 januari
A21: 20 | B21: PEMBANGUNAN TRANSMISI 150 KV CIKUPA NEW - INC. (TERMASUK 2 TOWER TX JATAKE - JATAKE) (PENGADAAN ULANG) | C21: 793576000 | D21: 38124351880 | F21: KSO SAJ TKAD | K21: sudah lunas, kemungkinan FAT Januari, tanggal 13 Januari FAT menunggu konfirmasi dari SAJ
A22: 21 | B22: TENDER ULANG PEKERJAAN PEMBANGUNAN EXTENSION 1 TRAFO BAY+TRAFO 30MVA GARDU INDUK 150KV SATUI | C22: 218213900 | D22: 30496332477 | F22: PT Citra Bakti Persada | K22: sdh ngasih harga menunggu update PLN Site, sdh minta dukungan, menunggu update site terakhir FU tgl 01/12, order via infotech, IAG beli ke infotech
A23: 22 | B23: PENGADAAN DAN PENGGANTIAN BUSHING P0 FASA R BAY 150/20 KV TRAFO#2 GI GANDAMEKAR DAN FASA S BAY 150/20 KV TRAFO#3 GI JABABEKA | C23: =D23*3% -> 20985150 | D23: 699505000 | F23: PT. ENINDO ORBITAMA | K23: masih proses approval dan masih proses produksi bushing, masih menunggu hasil survei, tgl 27 info dari user menunggu kedatangan barang, kemungkinan awal tahun 2026
A24: 23 | B24: PENGADAAN DAN PENGGANTIAN BUSHING TERSEBAR DI WILAYAH UPT BANDUNG | C24: =D24*3% -> 55869420 | D24: 1862314000 | F24: PT. ENINDO ORBITAMA | K24: masih proses approval estimasi sept - okt datangnya material bushing, tgl 27 info dari user menunggu kedatangan barang kemungkinan awal tahun 2026
A25: 24 | B25: PEMBANGUNAN TRANSMISI 150 KV TUBAN – PACIRAN SEKSI 1 & 2 | C25: =6460927340+6178468898 -> 12639396238 | E25: Seksi 1 Sangkan, Multifab, Indisi, WST, Seksi 2 Sangkan, HKP, Hasta Praja | F25: PT. Nusantara Power Construction, Indisi | K25: Closing 29 des, FU 04/11 BAP Sangkan, WST (sedang cari pasangan), HP, Indisi (ditolak sama plp), HKP (tdk ikut karna sudah yang punya), diundur 12/01 | N25: Marul
A26: 25 | B26: GITET BALARAJA | C26: 39366000 | F26: PT. ENINDO ORBITAMA | K26: masih proses approval dan masih proses produksi bushing, menunggu GIS sekitar 8 bulan lagi kemungkinan awal tahun 2026
A27: 26 | B27: PENGADAAN PEKERJAAN PEMBANGUNAN BAY COUPLER GARDU INDUK PARINGIN | C27: 251499948 | F27: PT. ENERGI ENTELEMI INDONESIA | K27: menang, verifikasi kontrak, sedang direview tim purchasing dan project untuk list supplier dan vendor penawaran harga sesuai kebutuhan kontraktor sdh dikirim dan direview oleh kontraktor, FU 05/01 pak Alvin minta waktu ketemu
A28: 27 | B28: PENGADAAN DAN PENGGANTIAN SEALING END GIS 150 KV UPT CAWANG TAHAP 2 | C28: 26190000 | F28: PT. SANTOSA ASIH JAYA | K28: Menang, FU 09/12 projek tahun depan
A29: 28 | B29: PENGGANTIAN SKTT 150 KV PEGANGSAAN – WAHANA | C29: 41973000 | F29: PT. SANTOSA ASIH JAYA | K29: Menang, FU 09/12 projek tahun depan
A30: 29 | B30: PENGGANTIAN MTU P0 WILAYAH UPT PURWOKERTO TAHUN 2025 | C30: 14956600 | F30: PT. GARDA PERDANA SECURITY | K30: menang, on site awal bulan desember, FU jeko terakhir 12/12 belum ada update lagi, jeko FU 19/12 tidak ada respon
A31: 30 | B31: JASA PENGGANTIAN MTU BOTTLENECK DI UPT GANDUL | C31: 345816000 | F31: PT SIMBARHOL TEKNIK PERKASA | K31: menang, sdh mulai pek. Gudang terlebih dahulu, FU terakhir 02/12 masih mengerjakan pekerjaan sipil (gudang) material MTU kemungkinan onsite tahun depan, jeko FU 19/12
A32: 32 | B32: EPC Poigar-2 HEPP Contactor BIDDING (2x15MW) / Pelelengan Kontraktor EPC PLTA Poigar-2 (2x15MW) | C32: =885100+55584000 -> 56469100 | D32: karena harga satuan | F32: PT Berca Buana Sakti | K32: closing 19/09 sdh dikirim ke BBS harganya, Pak Marul FU 18/08, tender EPC kontrak 6 bulan - 1 tahun
A33: 33 | B33: PENGADAAN DAN PENGGANTIAN TRAFO KONDISI BURUK WILAYAH TIMUR UITJBB LINGKUP JASA PENGGANTIAN TRAFO KONDISI BURUK DI GI CITRA HABITAT | C33: 55545000 | F33: PT DUTA CAKRAWALA INDONESIA | K33: menang sdh ttd kontrak, nabil FU ke pak Veri dan pak Abroham 01/12, pak Abroham tanya ke pak Veri tapi belum ada approval masih dalam tahap survey
A34: 34 | B34: PENGADAAN DAN PENGGANTIAN POLA PROTEKSI TERSIER IBT DI UPT MALANG | C34: 21495000 | F34: PT PAS Jaya Mandiri | K34: proses approval TPG, jeko FU 05/12 ke pak Eko nanti dikabari jika akan PO, FU 05/01 jeko
A35: 35 | B35: STRINGSET PURUK CAHU SECTION 1 | C35: 1990941480 | F35: KSO KE AMSAK | K35: kontrak PLN Kalbar, sdh penawaran harga ke kontraktor, Marul FU ke Pak Anrizal
A36: 36 | B36: Insulator GIG Puruk Cahu Sec 1 | C36: 1234440000 | D36: sudah dengan pengiriman | F36: KSO KE AMSAK | K36: kontrak PLN Kalbar, Marul FU ke Pak Anrizal
A37: 37 | B37: Relokasi Tower Cibatu | C37: 639294000 | F37: PT. Jaring Rainan Hutama | K37: sudah 100% pembayaran alam sdh PO ke PLP SOA line 1 dan 6 tanggal 16/01 sisanya 22/12, menunggu revisi ITP dan FAT, menunggu jadwal FAT test dari PLP
A38: 38 | B38: Relokasi Tower Jonggol | C38: 50401508 | F38: CMS | K38: Pak Asep proses DED & BED terakhir update 15/10, closing 12/09, estimasi project agustus sampai september 2026, laely FU 08/12 atau 09/12
A39: 39 | B39: BUKIT INDAH TL 150 KV | C39: 1910248200 | F39: PT. Nusantara Power Construction | K39: sudah pemasukan pembukaan sampul internal dari EPC swasta kemungkinan Februari 2026,
A40: 41 | B40: PEKERJAAN PENGADAAN DAN PEMASANGAN EXTENSION BAY TRAFO 4 DI GI 150 KV KUDUS | C40: 340573700 | F40: PT. AMSAK BANGUN PERSADA, | K40: Closing 04/09, Menang, menunggu approval drawing dan PO, sudah ada diskon PLP, 30-31/12 konsiyering AMSAK dan PLP di GI kudus
A41: 42 | B41: PEKERJAAN PEMBANGUNAN EXTENSION IBT 275/150 KV GITET TENTENA 2 X 250 MVA | C41: =1545477120 -> 1545477120 | F41: PT PLN NUSANTARA POWER CONSTRUCTION | I41: Menunggu penawaran PLP | K41: Closing 09/10/2025, NPC sdh dapat SPM, FU 15/12
A42: 43 | B42: PEMBANGUNAN EXT 1 TR BAY TRAFO KE 4 150/20 KV 60 MVA GI MODERN LINGKUP JASA PEMASANGAN | C42: 81313000 | F42: PT. Duta Cakrawala Indonesia | K42: Closing 2/10/2025, DCI Menang, FU mbak nabila ke pak Veri, proses approval
A43: 44 | B43: PEMBANGUNAN BAY TRAFO 3x60 MVA | C43: 401442000 | F43: KSO PT. AHZA JAYA MULIA, | K43: Closing 13/10/2025, masih pembukaan sampul 2, jeko FU 19/12 3 minggu blm ada respon
A44: 46 | B44: PEMBANGUNAN SKTT 150 KV BUDI KEMULIAAN – KEBON SIRIH | C44: 49541744 | F44: PT. High Volt Technology | K44: Closing 26/11/2025, FU 09/12 mba laely evaluasi tender
A45: 48 | B45: PEKERJAAN GARDU INDUK 150 KV DI SULAWESI | C45: 1770781200 | F45: PT. High Volt Technology | K45: Hanya minta harga, laely FU 05/12 belum ada info dari user ke Pak Syahrul
A46: 49 | B46: PENGADAAN DAN PENGGANTIAN BUSHING PRIMER PHASA S BAY TRAFO#4 150/20 KV GI JABABEKA | C46: 4717500 | F46: PT. ENERGI ENTELEMI INDONESIA | K46: Closing 22/10/2025, info dari pak ivan sedang ditanyakan ke tim tender, minta waktu untuk ketemu januari
A47: 51 | B47: PEMASANGAN EXTENSION IBT-2 GI 150/70 KV GI 150 KV NEW PONOROGO 100 MVA | C47: 189441300 | F47: PT. GLOBAL TWINSTAR | K47: Closing 22/10/2025, GTS menang, masih menunggu negosiasi harga, FU 16/12 mba laely masih survey
A48: 52 | B48: PENGGANTIAN AIR BUSHING DI WILAYAH UITJBB | C48: 11949000 | F48: PT. ENINDO ORBITAMA, | K48: Closing 22/10/2025, menunggu kedatangan barang kemungkinan awal tahun 2027
A49: 53 | B49: PENGGANTIAN AIR BUSHING GISTET KEMBANGAN DAN CAWANG BARU | C49: 11949000 | F49: PT. ENINDO ORBITAMA, | K49: Closing 22/10/2025, menang, menunggu kedatangan barang kemungkinan awal tahun 2027
A50: 56 | B50: PEKERJAAN PEMBANGUNAN SKTT 150 KV TX 1 – TX 2 TANJUNG API API | C50: 15716400 | F50: PT. MULTI FABRINDO GEMILANG | K50: Closing 27/11/2025, evaluasi sampul 1
A51: 58 | B51: PENAMBAHAN TOP GROUNDING (MDG) | C51: 2872500 | F51: PT. Cahaya Karya Bersama | K51: Closing 07/11/2025
A52: 59 | B52: PEKERJAAN PEMBANGUNAN SUTT 150 KV DUMAI – LUBUK GAUNG | C52: 4609605000 | F52: PT. Sapta Guna Utama, KSO PT. DALIMA PUTRA PERDANA – PT. BINA NOVITA, PT. TWINK INDONESIA | K52: Closing 28 November, dalima harga terendah, evaluasi teknis, FU 05/01 | N52: Marul
A53: 60 | B53: PEMBANGUNAN SKTT 150 KV KEDINDING – TX UJUNG, KEDINDING – TX KENJERAN DAN KEDINDING – TX BANGKALAN | C53: 177295200 | F53: PT. MULTI FABRINDO GEMILANG | K53: 22/12 proses klarifikasi tender
A54: 63 | B54: PEMBANGUNAN SKTT 150kV TAMBUN II – TX PONCOL BARU II | C54: 118418700 | F54: PT. MULTI FABRINDO GEMILANG | K54: Closing 27 November, evaluasi sampul 1
A55: 64 | B55: ENGINEERING PROCUREMENT & CONSTRUCTION 150 KV AIS SUBSTATION & TRANSMISSION LINE | C55: 1801435400 | F55: PT. Indokomas Buana Perkasa, Percie, HKP | K55: menang, Closing 19 November, FU marul 02/12 memberikan update penawaran untuk ABI, FU marul 03/12 masih klarifikasi teknis, evaluasi sampul 1 | N55: Marul
A56: 65 | B56: PEKERJAAN PEMBANGUNAN GARDU INDUK 150 KV MATARAM EXT (2LB) & GARDU INDUK 150 KV MANTANG EXT (2LB) | C56: 816583600 | F56: PT. Indokomas Buana Perkasa | K56: Closing 9/01, addendum akan dikirim oleh pak Alvian
A57: 66 | B57: PEMASANGAN EXTENSION TRAFO 5 GI 150 KV NGORO 60 MVA | C57: 181904800 | F57: KSO Masatek | K57: Menang | N57: Laely
A58: 67 | B58: PEMASANGAN EXTENSION BAY TRAFO KE-5 GI 150 KV SEKARPUTIH 60 MVA | C58: 158393100 | F58: KSO Masatek | K58: Menang | N58: Laely
A59: 68 | B59: PEKERJAAN GI 150 kV PAYAPASIR EXT TRAFO (1x60) MVA | C59: 119861600 | F59: PT WISMA SARANA TEKNIK | K59: Closing 22/12
A60: 69 | B60: PEKERJAAN GI 150 kV KIM EXT TRAFO (1x60) MVA | C60: 467420200 | F60: PT WISMA SARANA TEKNIK | K60: Closing 22/12
A61: 70 | B61: PEMBANGUNAN GITET 500/150 KV KARAWANG BESERTA SUTET 500 kV KARAWANG - INC. (INDRAMAYU - DELTAMAS) | C61: =6707806677+2482335600 -> 9190142277 | F61: PT. Indokomas Buana Perkasa | K61: Closing 05/01/2026
A62: 72 | B62: PEKERJAAN RELOKASI TOWER KRITIS SISTEM TIMOR PT PLN (PERSERO) UNIT INDUK WILAYAH NUSA TENGGARA TIMUR | C62: 194092600 | F62: KSO PT. KELINCI MAS UNGGUL – PT. ARHADI FAJAR PERKASA | K62: Closing 21/12
A63: 73 | B63: PENGGANTIAN ISOLATOR POST PADA TIANG BETON TIPE I DI UPT BALI | C63: 109200000 | F63: PT MEGA ALFARIZKI | K63: SOA 20/03
A64: 75 | B64: GI MARGAKARYA | C64: 95634000 | F64: PT GRIDTECH | K64: Proses approval drawing
A65: 77 | B65: GI KELAPA EXTENTION TRAFO BAY | C65: 141845700 | F65: PT INFORMATION DATA SYSTEM | K65: Proses approval drawing
A66: 79 | B66: JASA PERBAIKAN ANOMALI SUTT DAN SUTET UPT SEMARANG BULAN JANUARI 2026 - APRIL 2027 | C66: 190345500 | F66: PT Cahaya Karya Bersama | K66: Closing 05/01/2026
A67: 81 | B67: SUTET 275 KV GGL Additional | C67: 109968000 | F67: PT. CITRAMASJAYA TEKNIKMANDIRI | K67: material sudah di gudang UGC
A68: 83 | B68: PEMBANGUNAN SUTT 150 KV MATARAM – MANTANG | C68: 2135074372 | F68: KSO PT. PURNAMA INDONESIA - PT. NIAGAMAS SETIAUSAHA | K68: pengumuman pemenang: Purnama
C69: 88310592

Sheet Progress 2024
B1: Progres 2024 | C1: =SUM(C3:C6) -> 2457867693
A2: No | B2: Project Name | C2: Value excl. PPN | D2: Status | F2: CUSTOMER | G2: Desc | H2: Factory Promise | I2: Remarks Kontraktor | J2: Remarks Principle | K2: Remarks AI | L2: INSULATOR | M2: Remarks | N2: PIC | O2: Keterangan
A3: 1 | B3: Perbaikan Anomali Jaringan di UPT Bandung | C3: 475955700 | D3: Sudah PO | E3: sisa | F3: PT. Cipta Daya Utama | K3: cicilan pertama 7 Desember 25.000.000, sisa utang 344 Jt, cicilan kedua Januari 2025 sebesar 50 jt, sisa 214 jt, CDU akan bayar setiap tgl 25 sebesar 50jt, 28 Feb 30 jt, 28 mei bayar 50 jt sisa 164jt, janji bayar 27 Juni, 30 juni bayar 30jt sisa 134 jt, info dari Pak Sudaryo, bulan ini akan melakukan pelunasan ke PT Alam di minggu ke 4. Untuk tanggal pasti pembayarannya belum ada update terbaru lagi, 04/08 dibayar 54 jt sisa 80 jt, sisa 49.999.982, terakhir bayar 29 Agustus 30.817.597
A4: 2 | B4: JASA PENGGANTIAN KAWAT GSW BERIKUT STRINGSETNYA PADA SUTET 500 KV BANDUNG SELATAN - NEW UJUNG BERUNG T.34-80, SUTT 150 KV PADALARANG BARU - CIRATA T.01-T.26, DAN BANDUNG SELATAN - KIARACONDONG T.50-T.62 | C4: 339839820 | D4: 1.931.400.000 (Nilai Kontrak) sdh dicicil 50jt sisa 289.839.820 mega sudah mengajukan VIP sejak tgl 14 Feb | E4: amandemen s/d 2 January 530 hari sdng pengajukan perpanjangan 90 hari s/d 2 april 25 mulai kerja feb sdh dicicil 50jt, yg blm pdlrng - cirata T12 -22 Bansel - Uber T.34 - 50 akan di kerjakan feb, ada jadwal padam lagi 11-12 Jan pdlng baru - cirata line 1 18-19 jan bansel-new uber, minta dicicil | F4: KSO Mega Alfarizki - Indodaya Naratama Abadi | K4: BAST sudah dikirim dibulan Januari Pengajuan restitusi di bulan april estimasi 3 - 4 bulan sampai dengan agustus. Sudah FU bulan Juni, masih on process. Akan di FU kembali ke MA pada bulan Juli, masih restetusi 32jt (perkiraan agust), belum cair FU Bu diyah tgl 4/08 | M4: Kontrak 23 Juni 2023 masa berlaku kontrak 365 hari, pekerjaan dimulai 27-28 January dan 3-4 Feb 2024 ada kendala GSW putus di tower 50 (Bandung Selatan - New Uber), 22 Jan pekerjaan unclamping dari tower 34 - 62 (ada 4 tim), dan 22 jan haspel dan repair sleeve proses , Pemadaman 22 April - 25 April dan 29 April - 2 Mei 2024 T. 58-62, renc. tgl 22 pekerjaan di T. 58, 50, 51, 55 unclamping, tgl 11-12 T.12-T. 21 terakhirnya 18-19 Mei T. 24 - 26, rencana padam ganti GSW T. 1 - T. 22 PDRU Cirata Line1 22-23 juni line 2 T.1-T.22 29-30 Juni T.24-T.26 Cirata Line 6 Juli Line T.24-T.26 7 Juli, pasar steger pdlrng - cirata T.1-T.22, sdng proses pek. T.72-80 new Uber,06/02/2025 final quantity, BAST sudah Januari
A5: 5 | B5: Retender GSW 500 KV UPT Bogor | C5: 1642072173 | D5: 5685626000 | E5: Saguling - cibinong T.21&22 - T.38, T.111 - 139 sdh selesai blm ada jadwal lagi, update terakhir pekerjaan 75% | F5: Konsosium Mega Alfarizki - Indodaya Naratama Abadi,PT | I5: Closing tgl 23 Agustus 2023 | K5: menunggu jadwal padam jalur Cilegon. Penagihan mega sudah termin 2 dari mega pengen minta perhitungan PPH dan fee admin seperti perhitungan project bandung, sdh bayar 200jt tgl 5 Juni. FU tanggal 14 koordinasi dlu ke bagian finance, sisa termin 1 dan termin 2 sisa 269jt total tagihan PO 848jt | M5: kontrak tgl 25 September 2023, pelaksanaan 720 hari sejak kalender, barang sudah disite semua dan sdh pemeriksaan barang tgl 11 Jul, rencananya dit. Kapan jadwal padam 29 Jul - 16 Agus tetapi MAnya msh blm ada konfirmasi 24 Jul, ada usulan tgl 2-6 des, 9-13 des. Jalur saguling - cibinong, 18-19 dan 25-26 jan 2025 jalur cilegon - cibinong bln feb saguling cibinong 2, tgl 19 jadwal padam cibinong-saguling 8-17 des line 1, saguling cibinong 2 T134-T.152 tgl 3-7 feb, tgl 8-9 feb Cilegon-cibinong , tgl 10-14 feb saguling-cibinong 2, tgl 17-21 saguling-cibinong 2, tgl 24-28 saguling-cibinong 2
A6: 7 | B6: PENGADAAN DAN JASA PENGGANTIAN KABEL 66 KV TERSIER IBT 2 GITET UNGARAN | D6: 6184864900 | E6: kontrak tgl 25 Jun - 25 Feb 2025, FAT sdh & Material sdng dikirim datang sekitar 2 des dipick up masatek | F6: UPT Semarang | G6: KSO Masatek - INA, menunggu klarifikasi sampul 1 | K6: kabel sdh datang di GI Ungaran, Jumat 1 Nov meeting dgn pak ayub membahas sipil, sealing end trimitra tdk jadi thn ini luncur ke tahun depan, masih direview BOQ Sipil kerja (+-), sealing end sdh sampai mulai kerja ditgl 9 - 31 jan, supervisi arkasil di tgl 1-12 maret, EOT Prafinal Quantity sampai sekarang pekerjaan 70%, menunggu pek. MTU dari induk estrimasi bln agustus, pak ayub : aspal sdh dikerjakan dan penambahan linkbox bobot sekitar 92%, sdh bayar termin 2 tgl 11/07 560jt tanpa PPN, termin 3 sdh dibayar tgl 27/09 543jt

Sheet Progress 2023
B1: Progres 2023 | C1: =SUM(C3:C28) -> 56442386959
A2: No | B2: Project Name | C2: Value excl. PPN | D2: Status | F2: CUSTOMER | G2: Desc | H2: Factory Promise | I2: Remarks Kontraktor | J2: Remarks Principle | K2: Remarks AI | L2: INSULATOR | M2: Remarks | N2: PIC | O2: Keterangan
A3: 1 | B3: PEMBANGUNAN TOWER RELOKASI TRANSMISI AIR ANYIR - PANGKALPINANG LINTASAN SUNGAI BATU RUSA | C3: =288802500+344822400 -> 633624900 | D3: Sudah PO | F3: PT Tesla Daya Elektrika | K3: pekerjaan addendum sampai maret 2024, sudah PO INA ke Sicame untuk stringset, insulator tidak jadi di PO ke INA karna tidak ready stock, sudah DP 20%, menunggu update sicame | M3: Selasa Adel Fu kontraktor lagi | N3: Adel
A4: 2 | B4: JASA PEMASANGAN MTU DAN PENGADAAN ALAT UJI DI WILAYAH UPT SEMARANG | C4: 214722900 | F4: PT. Global Twin Star | K4: Pemenang Tender, Menunggu PO & approval drawing dari kontraktor, baru ttd kontrak 20 Nov 2023, update tgl 15 info dari GTS pakai eksisting | L4: 270
A5: 3 | B5: Perbaikan Anomali Jaringan di UPT Bandung | C5: 475955700 | D5: Sudah PO | F5: PT. Cipta Daya Utama | K5: cicilan pertama 7 Desember 25.000.000
A6: 4 | B6: Pengadaan dan Jasa Penggantian String Set serta Isolator 120 kN untuk SUTT 150kV Purbalingga - Rawalo T.94-172 | C6: 3186135459 | D6: Sudah PO | F6: Perintis Sarana Elektrik, PT | G6: Pengadaan dan jasa | I6: Pembayaran Back to back | J6: Minta penawaran harga terbaru | K6: menunggu retensi 5%, 176.830.518, BAST 22 Mei 2023 Retensinya Mei 2024 | M6: PO Perintis Back to Back, INA sudah DP 20% ke Sicamindo, Material siap di pick up minggu ke 3 Desember 2022 di balaraja oleh kontraktor | O6: Pastikan material selesai kapan.
A7: 5 | B7: JASA PENGGANTIAN KAWAT GSW BERIKUT STRINGSETNYA PADA SUTET 500 KV BANDUNG SELATAN - NEW UJUNG BERUNG T.34-80, SUTT 150 KV PADALARANG BARU - CIRATA T.01-T.26, DAN BANDUNG SELATAN - KIARACONDONG T.50-T.62 | C7: 339839820 | D7: 1931400000 | F7: KSO Mega Alfarizki - Indodaya Naratama Abadi | K7: Kontrak 23 Juni 2023 masa berlaku kontrak 365 hari, PO pertama repair sleep sudah ready, PO ke Sicame (midspan joint as 70, vibration damper,armour rod dan shackle), jadwal pekerjaan dimulai 13-14 January dan 27-28 January (Bandung Selatan - New Uber) haspel sewa gudang sampai 12 January 2024, material 150kV masih disortir
A8: 6 | B8: JASA PENGGANTIAN ISOLATOR BERIKUT STRINGSET DI T.1 S/D T.54 SUTT 70KV PURWAKARTA – KOSAMBI BARU – SOUTH PASIFIC | C8: 1017196840 | D8: UPT Karawang INA tidak bisa konsorsium dikarenakan tidak punya pengalaman | E8: harga diatas sudah termasuk diskon kerawang dan semarang masing" 5% | F8: PT MEGA ALFARIZKI | K8: Sudah DP 10%, SOA 19 Jan 3 item sudah diambil tgl 11 Des GIRO 30 January 2024, sisanya 21 Des sudah diambil
A9: 7 | B9: JASA PENGGANTIAN EARTH WIRE BERIKUT STRINGSETNYA PADA SUTT PANDEANLAMPER – PUDAKPAYUNG T. 14-33 DAN SUTT TAMBAKLOROK-UNGARAN T.29-45 SERTA JASA PENGGANTIAN STRINGSET TOWER SUTT TAMBAKLOROK-UNGARAN T.01-12 AKIBAT KOROSI | C9: 579778800 | D9: UPT Semarang | F9: PT MEGA ALFARIZKI | K9: DP sudah 10% SOA 8 Desember sudah diambil tgl 11 Des, GIRO 30 January 2024
A10: 8 | B10: PEMBANGUNAN TRANSMISI 150 KV PAKNING- SIAK: LOT 1&2 | C10: 12211780546 | E10: Sumatra | F10: Sapta Guna Utama, PT | I10: penjelasan 3 Agustus 2023, closing 13 September 2023 | K10: Aanwijzing tanggal 21 Juli 2023, Closing 15 Desember 2023
A11: 9 | B11: PEMBANGUNAN TRANSMISI 150 KV SEI DURIAN - TARJUN: LOT 1&2 | C11: 15948442300 | E11: Kalimantan | F11: Distraco, PT | I11: penjelasan 2 Agustus 2023, closing 14 September 2023 | K11: 17 Januari pembukaan sampul 1
A12: 10 | B12: PEMBANGUNAN TRANSMISI 150 KV TANAH GROGOT - SEI DURIAN LOT: 1&2 | C12: 6933786700 | E12: Kalimantan | F12: Distraco, PT | I12: penjelasan 2 Agustus 2023, closing 14 September 2023 | K12: 17 Januari pembukaan sampul 1
A13: 11 | B13: Retender GSW 500 KV UPT Bogor | C13: 1642072173 | D13: 5685626000 | F13: Konsosium Mega Alfarizki - Indodaya Naratama Abadi,PT | I13: Closing tgl 23 Agustus 2023 | K13: kontrak tgl 25 September 2023, pelaksanaan 720 hari sejak kalender, asli kontrak sudah diterima jampel sudah diterima PLN sedang proses approval drawing sudah nen menunggu PO dari mega INA PO ke Sicame, euis FU 18 Des
A14: 12 | B14: GI Batu Raja Stringset | C14: 272252800 | E14: Sumatra | F14: Masatek | I14: Penawaran harga&drawing hari ini tgl 21 Agustus 2023 | K14: revisi drawing dan harga sudah dikirim ke kontraktor FU 21 Nov 2023
A15: 13 | B15: GI Batu Raja Insulator | C15: 177514000 | E15: Sumatra | F15: Masatek | I15: Sudah PO, alam belum PO ke DALIAN | K15: Insulator Laely PO Hari ini, sudah DP 20%
A16: 14 | B16: DIES AI DI Mega Tech | K16: Pengambilan direncanakan minggu ini
A17: 15 | B17: 2X25MWP BALI SOLAR PV CONSTRUCTION AND INSTALLATION 150KV TRANSMISSION LINE PT. Medco Solar Bali Barat | C17: =858542720+1026788400 -> 1885331120 | F17: Niagamas Setia Usaha,PT | I17: Masih proses evaluasi dan teknis, Closing tgl 28 Juli 2023 | K17: Closing 2 Agustus 2023, pembukaan sampul 1, belum ada keputusan dari medco, FU tgl 11 Desember
A18: 16 | B18: 2X25MWP BALI SOLAR PV CONSTRUCTION AND INSTALLATION 150KV TRANSMISSION LINE PT. Medco Solar Bali Timur | C18: =315601552+417879000 -> 733480552 | F18: Niagamas Setia Usaha,PT | I18: Masih proses evaluasi dan teknis, Closing tgl 28 Juli 2023 | K18: Closing 2 Agustus 2023, pembukaan sampul 1, belum ada keputusan dari medco, FU tgl 11 Desember
A19: 17 | B19: PENGADAAN DAN PEMASANGAN 1 BAY REAKTOR 30 MVAR | C19: =144762500+125820000 -> 270582500 | F19: Lembah Sentral Elektronindo, PT | I19: sudah PO ke PLP kontraktor minta minggu ke 3 February | K19: paling lambat oktober delivery maret 2024, terakhir kontraktor minta bulan febuari 2024 alam sudah komunikasi dengan pak tengku SOA 12 February 2024 sudah dp 20%
A20: 18 | B20: Penyempurnaan instalasi gedung dan perlengkapan K3 GIS Penggilingan II dalam rangka penyelesaian pending STP | C20: 232113950 | F20: PLN UPT Pulogadung | I20: sisil nunggu scan BA dari UPT baru di upload ke VIP | K20: kontrak tgl 13 nov 2023, sudah submit tgl 10 Desember 2023, dana ditahan UIP upload di VIP jadi January 2024 (Kekurangan BAP)
A21: 19 | B21: DESAIN, SUPLAI DAN PEMASANGAN GITET 500 KV KALIPURO | C21: 5982203000 | F21: PT. WIJAYA KARYA (Persero) Tbk | I21: Mbak Laely temui kontraktor | K21: Closing tgl 21 November 2023, Klarifikasi Teknikal disamakan dengan permintaan PLN, klarifikasi ke 2 sudah dikirim tgl 11 Des menunggu evaluasi sampul 1
A22: 20 | B22: Jasa EPC Pembangunan Gardu Induk 150kV untuk Penyambungan Tenaga Listrik PLN ke UBPN Kolaka | C22: 978017535 | F22: PT. High Volt Technology | I22: Sudah PO Menunggu approval drawing dari Antam | K22: Sudah PO, revisi Approval Drawing, minggu ini ada agenda zoom meeting (PLP. HVT, Antam), FU tgl 18 Des, Menunggu DP, setelah DP akan di PO ke PLP
A23: 21 | B23: JASA PENANGANAN ANOMALI JARINGAN DI WILAYAH UPT KARAWANG TAHUN 2023 | C23: 7005400 | F23: PT MEGA ALFARIZKI | I23: FU minggu ini apakah sudah ada kebutuhan KHS-nya | K23: FU 11 Des 2023, Kapan kebutuhannya
A24: 22 | B24: PENGGANTIAN CELL KAPASITOR 50MVAR DI GI 150KV KALIWUNGU | C24: 50000000 | D24: UPT Semarang | F24: Masatek | I24: Klarifikasi Harga | K24: Closing 22 November 2023
A25: 23 | B25: Pembangunan GI 150kV Tanggeung / Cianjur Selatan | C25: 600000000 | F25: PT. Buanareksa Binaperkasa, Mega Power | I25: masih evaluasi sampul 1 | K25: Mega Power menang, kami masih blm evaluasi vendor2 yg mendukung
A26: 24 | B26: UPRATING 2 LB GI 150 kV LAMONGAN BAY CERME 1,2 | C26: 377296766 | F26: PT. Global Twin Star, PT. Bina Buana Sewaka, PT Masatek | I26: Pemenang tender GTS | K26: GTS Menang, sudah dikirim ke kontraktor design baru stringset tanpa arching horn
A27: 25 | B27: Pekerjaan rekonfigurasi GIS Tandes TL Bay Ujung ke PKB #l dan TL Bay Perak ke PKB #2 | C27: 292034400 | E27: 775758900 | F27: PT. Mahakaam Jaya Sejahtera | I27: baru akan proses CDA lalu ttd kontrak | K27: Pemenang tender 6.185.031.000 FU 27 Nov, masih proses CDA
A28: 26 | B28: UPRATING LINE BAY GI 150KV BABAT DAN GI 150KV LAMONGAN | C28: 1401218798 | F28: PT. Global Twin Star | I28: Insulatornya ABI Stringsetnya PLP, masih menunggu klarifikasi teknikal | K28: Klarifikasi sampul 1
A29: 27 | B29: Pengadaan material untuk pemeliharaan di wilayah UPT Bogor | C29: 2318307208 | F29: PT. Indodaya Naratama Abadi | I29: Closing 12 Desember, Jumat 8 harus sudah selesai semua | K29: Closing 12 Desember, masih evaluasi sampul 1 INA DML Trisco
A30: 28 | B30: PEKERJAAN PEMBANGUNAN SUTT 150 KV JERANJANG – SEKOTONG DAN GI 150 KV JERANJANG EXT. (2LB) | C30: =337749700+297300+3217636000 -> 3555683000 | F30: KSO PT. PURNAMA INDONESIA – PT. KENCANA ALAM PUTRA | I30: Closing 10 November | K30: Lolos sampul 1
A31: 29 | B31: PEMBANGUNAN EXT 1 TR BAY TRAFO KE 4 150/20 KV 60 MVA GI CIKANDE LINGKUP JASA PEMASANGAN | C31: 51325500 | F31: PT INDEVCO GLOBAL | I31: Closing 4 Desember | K31: Tender ulang semua sudah disubmit ulang
A32: 30 | B32: PEMBANGUNAN GI 150 KV PAKNING | C32: 1995973400 | F32: PT SAPTA GUNA UTAMA | K32: Closing 15 Desember
A33: 31 | B33: PEMBANGUNAN BAY KOPLER 150 KV GI SAMBUTAN PT PLN (PERSERO) UNIT INDUK PENYALURAN DAN PUSAT PENGATUR BEBAN KALIMANTAN | C33: 276864600 | F33: PT. DISTRACO | K33: Closing 6 Desember, Distraco menang besok CDA
A34: 32 | B34: PEMBANGUNAN EXT 1 TR BAY TRAFO KE 3 150/20 KV 60 MVA GI PUNCAK ARDI MULYA II (GI MODERN) LINGKUP JASA PEMASANGAN | C34: 57130500 | F34: PT INDEVCO GLOBAL | I34: Closing 5 Desember | K34: Tender ulang semua sudah disubmit ulang
A35: 33 | B35: EXTENSION 1 BAY TRAFO 150/20KV NGORO (PEMASANGAN EXTENSION 1 BAY TRAFO 150/20KV NGORO) | C35: 281838100 | F35: PT. Purnama Indonesia, Binabuana Sewaka, Buanareksa | I35: Closing tgl 15 Desember | K35: Masih evaluasi sampul 1
A36: 34 | B36: PENGADAAN DAN PENGGANTIAN ISOLATOR KONDISI KRITIS TERSEBAR DI UNIT TRANSMISI JAWA BAGIAN TIMUR DAN BALI (PENGADAAN ISOLATOR KOMPOSIT) | C36: 1474722000 | F36: PT. Kencana Alam Putra, Purnama Indonesia | K36: Closing tgl 22 Desember, masih evaluasi
A37: 35 | B37: PENGADAAN DAN PEMASANGAN REAKTOR 70 KV GARDU INDUK RUTENG SISTEM FLORES | C37: 216170300 | F37: PT. Lembah Sentral Elektronindo, Mulya Jatra | I37: Closing tgl 19 Desember | K37: Lolos sampul 1
A38: 36 | B38: PENANGANAN TOWER T-73 DAN T-75 SUTT 70KV NONOHONIS – KEFAMENANU SISTEM TIMOR | C38: 121924300 | F38: PT. SINERGI PROPERTI PRATAMA | K38: Menunggu aproval Drawing
A39: 37 | B39: PENGOPERASIAN IBT 6 KRIAN | F39: PT. Buanareksa Binaperkasa | K39: Closing 29 Desember, Menunggu penawaran harga dari PLP
A40: 38 | B40: PEMASANGAN EXTENSION 1 BAY TRAFO 150/20 KV TULUNGAGUNG II | F40: PT. Global Twin Star | K40: Closing 10 Januari 2024, Menunggu penawaran harga dari PLP

Sheet Progress 2022
B1: Progres 2022 | C1: =SUM(C3:C21) -> 10164493393
A2: No | B2: Project Name | C2: Value excl. PPN | D2: Status | E2: CUSTOMER | F2: Desc | G2: Factory Promise | H2: Remarks Kontraktor | I2: Remarks Principle | J2: Remarks AI | K2: INSULATOR | L2: Remarks | M2: PIC | N2: Keterangan
A3: 1 | B3: Pengadaan dan Pemasangan Kapasitor di Gl Puger 1x25 Mvar (Tahap 2) | C3: 150385000 | D3: Sudah PO | E3: PT MAHAKAAM JAYA SEJAHTERA | F3: STRINGSET DAN HV CONNECTOR | H3: PO DP 20%, Kontraktor mau pick up barang disatu tempat (Gudang UGC) | J3: Baut sudah dikirim, Tanggal Giro 10 January 2023, FU Dita
A4: 2 | B4: PENGGANTIAN KAWAT PETIR ACSR MENJADI AS SUTT BANTUL-KLATEN; KENTUNGAN-MEDARI-SANGGRAHAN; BAWEN-SECANG-SANGGRAHAN; GODEAN-BANTUL; BAWEN-KLATEN | C4: 2127828100+C5 | D4: Sudah PO | E4: PT KARYA PUTRA GEMILANG / UPT Salatiga | F4: STRINGSET & FITTINGS | I4: SOA 224744 Material selesai tanggal 22-23 November 2022 | J4: Material sudah diambil 26 Desember 2022 GIRO tanggal 26 Maret 2023
A5: 3 | B5: PEKERJAAN PERBAIKAN ANOMALI JARINGAN DI UPT BANDUNG | C5: KHS | D5: Kontrak Payung sudah, Parsial pemesanan menunggu konfirmasi dari PLN | E5: CIPTA DAYA UTAMA, PT | F5: ACCESSORIES AS 55 & AS 70 | H5: Menunggu Approval drawing | J5: Perkiraan awal tahun 2023 FU mbak Laely, Nabil | L5: FU Mbak laely & Nabil | N5: Baru pengumuman pemenang
A6: 4 | B6: UPRATING BUSBAR 150 KV GI PINAYUNGAN | C6: 905947000 | D6: Sudah PO | E6: DUTA CAKRAWALA INDONESIA, PT | F6: Stringset&HVC | H6: Revisi drawing | J6: Material sudah dihitung lengkap dan sudah diambil, Cek sudah difinance tanggal 14 February 2023 | L6: FU Ikhbal
A7: 5 | B7: EXTENSION 1 LINE BAY GI 150KV PETROKIMIA UNTUK LAYANAN KTT PT SMELTING | C7: 135929980 | D7: Sudah PO | E7: GLOBAL TWIN STAR, PT | F7: Stringset&HVC | H7: Menunggu PO sudah final nego | J7: Barang sudah diambil GIRO tanggal 8 January 2023 FU Dita
A8: 6 | B8: PENGADAAN STRING SET EARTH WIRE AS 70 MM2 DAN JASA PENGGANTIAN STRING SET SERTA EARTH WIRE DI WILAYAH UPT PURWOKERTO | C8: 464025800 | D8: Sudah PO | E8: MEGA ALFARIZKI, PT | F8: Stringset | H8: Menunggu DP, Material selesai tgl 23/12/22 & 25/11/22 | J8: GIRO tanggal 15 January 2023, Material diambil tanggal 13 Desember 2022 FU Dita
A9: 7 | B9: PENGADAAN DAN JASA PENGGANTIAN DOUBLE STRING SET SERTA ISOLATOR 120 KN UNTUK SUTT 150 KV GOMBONG - RAWALO - KESUGIHAN T.35-99 | C9: 1809194400 | D9: Sudah PO | E9: CIPTA DAYA UTAMA, PT | F9: Stringset | H9: DP sudah masuk 30%, Material selesai tgl 04/11/22 | J9: Material sudah diambil tanggal 31 Oktober 2022 CEK baru tangal 28 February 2023 | L9: SOA 224785(28/10/2022) | N9: Cek perlu diganti
A10: 8 | B10: Pengadaan dan Jasa Penggantian String Set serta Isolator 120 kN untuk SUTT 150kV Purbalingga - Rawalo T.94-172 | C10: 3186135459 | D10: Sudah PO | E10: Perintis Sarana Elektrik, PT | F10: Pengadaan dan jasa | H10: Pembayaran Back to back | I10: Minta penawaran harga terbaru | J10: Material sudah di cek dan dihitung, material shackle sudah ready tanggal 30 Desember 2022, turnbuckle pengganti CDE QTY 360 PO Hariini dan material selesai tanggal 6 February 2023 Info ke sicame jangan pake sisa stock, Masih menunggu progres project Purbalingga - Rawalo | L10: PO Perintis Back to Back, INA sudah DP 20% ke Sicamindo, Material siap di pick up minggu ke 3 Desember 2022 di balaraja oleh kontraktor | N10: Pastikan material selesai kapan.
A11: 10 | B11: Additional JASA PENGGANTIAN TRAFO #2 GI 150 KV SEMANU | C11: 3585120 | D11: Sudah PO (2) | E11: GLOBAL TWIN STAR, PT | J11: Material sudah diambil tanggal 5 January 2023 Dita cek pembayaran harus sudah masuk tanggal 4 February 2023
A12: 11 | B12: JASA PENGGANTIAN TRAFO #2 GI 150 KV SEMANU | C12: 5949000 | D12: Sudah PO (2) | E12: GLOBAL TWIN STAR, PT | H12: Menunggu Approval Drawing, Kontraktor minta diskon | J12: Material sudah diambil tanggal 5 January 2023 Dita cek pembayaran harus sudah masuk tanggal 4 February 2023
A13: 12 | B13: Pengadaan SUTT 150KV Rawalo Star T01-55 | C13: 968389530 | D13: Sudah PO | E13: Perintis Sarana Elektrik, PT | H13: Minta harga diskon ke sicame, minta jasa ke kontraktor, Sudah DP 10%, Minta jadwal FAT | J13: Material sudah lengkap sisa pembayaran 467.421.140,47 (Termin 2)
A14: 13 | B14: PENGADAAN DAN PEMASANGAN KAPASITOR 1X50 MVAR GI 150KV PURWOSARI | C14: 16000000 | D14: Sudah PO | E14: Purnama Indonesia, PT | J14: Menunggu pembayaran, dan barang ready stock
A15: 14 | B15: PENGADAAN DAN PEMASANGAN RELAY BUSBAR PROTECTION DI GI 150KV LAGADAR, GI 150KV WAYANGWINDU, GITET 500KV BANDUNG SELATAN, GISTET 500KV SAGULING, GIS 150KV SIMPANG LIMA, DAN GI 150KV JEPARA | C15: 55740000 | D15: Menunggu Drawing MTU | E15: Kencana Alam Putra, PT | J15: Drawing untuk approval sudah diberikan ke Zaenal KAP, Tinggal menunggu respon
A16: 15 | B16: PENGADAAN DAN PENGGANTIAN GSW TERSEBAR DI WILAYAH ULTG KEDIRI DAN ULTG BABAT | C16: 1070328580 | D16: Sudah PO | E16: GLOBAL TWIN STAR, PT | F16: STRING SET | J16: SOA 224943 ( Dec 2022- Feb 2023), Material sudah dipick up, kekurangan material suspesion clamp (February) dan awar (January) Pak Dedy FU ke pak Teguh dan cek gudang alam GIRO tanggal 22 Maret 2023
A17: 16 | B17: PENGADAAN DAN PENGGANTIAN GSW TERSEBAR DI WILAYAH ULTG MADIUN | C17: 974998310 | D17: Sudah PO | E17: GLOBAL TWIN STAR, PT | F17: STRING SET | J17: SOA 224951 ( Dec 2022- Feb 2023), Material diambil parsial tanggal 17 January 2023 Suspension clamp dan Awar qty 350 pcs sisanya tanggal 17 February 2023 dan GIRO parsial yang pertama tanggal 21 Maret 2023 Cek bagian keuangan invoice PLP baru bisa diterbitkan jika sudah material semua selesai (setelah tgl 17 February 2023)
A18: 17 | B18: Pembangunan Ekstension 1 Line Bay Konsumen di GI 150kV Indoferro | C18: 112978000 | D18: Menunggu Kontrak | E18: Buanareksa Binaperkasa, PT | J18: Nabil FU ke buanareksa taggal 12 January 2023
A19: 18 | B19: Additional GIS Gunung Sari | C19: 35712614 | D19: Sudah PO | E19: Sastramas Estetika, PT | J19: SOA 20 January 2023 (PLP) Disk Insulator Ready stock (Kuarta) FU Dita
A20: 19 | B20: Perkuatan Proteksi Petir Tersebar Wilayah UPT Madiun | C20: 178000000 | D20: Menunggu Kontrak | E20: Persada Indah Muda, PT | J20: Menunggu approval drawing dari PLN
A21: 20 | B21: JASA PEMASANGAN MTU DI WILAYAH UPT PROBOLINGGO | C21: 91194600 | D21: Menunggu Approval Drawing | E21: Cahaya Karya Bersama, PT | J21: sedang menunggu revisi drawing dari principal untuk diajukan ulang ke PLN FU Euis
A22: 21 | B22: SUTT PLN UPT BEKASI | E22: Jati Mulia, PT - DUTA CAKRAWALA INDONESIA, PT | J22: Menunggu penawaran harga dari ALAM

Sheet Progres 2021
B1: Progres 2021
A2: No | B2: Project Name | C2: Value | D2: Status | E2: Nama Kontraktor | F2: Desc | G2: PLP Promise | H2: Remarks Kontraktor | I2: Remarks PLP | J2: Remarks AI | K2: INSULATOR | L2: Remarks | M2: PIC | N2: Keterangan
A3: 1 | B3: GI 150 kV Tawaeli | D3: Prospek | E3: NSU | F3: STRINGSET DAN HV CONNECTOR | H3: Update drawing dan harga sudah, menunggu nego Kontraktor dengan PLN | I3: - | J3: Menunggu informasi dari NSU drawing sudah diberikan ke kontraktor harusnya sudah di approval PLN, belum ngasih penawaran FU Pak Fuad | L3: Tunggu PO Kontraktor ke Alam | M3: Fuad | N3: menunggu info selanjutnya dari PLN
A4: 2 | B4: GI 150 kV Bunta | D4: Prospek | E4: NSU | F4: STRINGSET DAN HV CONNECTOR | H4: Update drawing dan harga sudah, menunggu nego Kontraktor dengan PLN | I4: - | J4: Menunggu informasi dari NSU drawing sudah diberikan ke kontraktor harusnya sudah di approval PLN | L4: Tunggu PO Kontraktor ke Alam | M4: Fuad | N4: surat pernyataan dari PLP, menunggu info selanjutnya dari PLN
A5: 3 | B5: TL 150kV TIP 12 PLN Smelter CNI Switchyard | D5: Prospek | E5: Owner : CNI | J5: Pak Fuad FU ke Bu Happy/Bu Zakhia | M5: Fuad | N5: Belum ada pengumuman dari PP, blm ada kabar
A6: 4 | B6: TL 150kV KID - Pakning Sec. 1, 2 & 3 | D6: Prospek | E6: Owner : Sumbagteng | J6: Pak Fuad FU ke Pak OktaPLN Sumbagteng | M6: Fuad | N6: FU Pak Fuad ke Pak Oktarico, pengumuan sec.3 saja (dihold)
A7: 5 | B7: Pengadaan Stringset dan Jasa Penggantian GSW Rantas dan Korosif SUTT 70kV KSBRU-RSDKL T.01 S/D T.103 Dan Antara Tower A76 - A86 SUTET 500kV Cirata - Deltamas 1-2 | C7: 314000000 | D7: Sudah PO | E7: Persada Indah Muda (Pak Pradana) | F7: Stringset | G7: 16 Juli 2021 | H7: DP dan Approval drawing sudah | J7: Material diambil 24 Aug 2021, cash + cover giro 31/12/2021 | M7: Fuad
A8: 3 | B8: PENGANTIAN GSW AS 55 (T.10-T.36) SUTT 150 KV CILEGON BARU - ASAHIMAS - POLYPRIMA | C8: 120000000 | D8: Sudah PO | E8: PT DUTA CAKRAWALA INDONESIA | G8: Akhir January 2022 | J8: Sudah DP, material selesai akhir January 2022
C22: =SUM(C3:C14) -> 434000000

Sheet Progress 2020
B1: Progress 2020
A2: No | B2: Project Name | C2: Nama Kontraktor | D2: Desc | E2: PLP Promise | F2: Remark Kontraktor | G2: Remarks PLP | H2: Remarks AI | I2: INSULATOR | J2: Remarks | K2: PIC | L2: Keterangan
A3: 1 | B3: 150KV GI LUWUK & TOILI | C3: Amanda | D3: STRINGSET DAN HV CONNECTOR, PROSES ANTRIAN | E3: DONE | F3: Tukar giro tanggal 2 Juni 2020 | H3: Pembayaran menggunakan giro, Giro sudah expired tgl 9 Maret 2020 , FU pak Fuad minggu depan tgl 15 Juni 2020 ke bu ratna | I3: PI 2 buah blm di ambil masih di marunda | J3: sudah 297 hari AR nya, bulan oktober sudah, november mencairkan cek tiap akhir bulan, FU Bag. Keu akhir bulan Desember 2020 dibayar januari 2021 | K3: Fuad | L3: 1. Sisa pembayaran 534 juta FU Pak Fuad untuk menanyakan kepastian pembayaran d bulan maret 2020, Cicil perbulan 100 jt (sudah masuk cicilan ke dua GI Toili) barang sudah diambil 2. PO Additional belum diambil (Nilai 32.128.800)
A4: 2 | B4: PAKET 2 BAY TRAFO BANDUNG | C4: Amanda | D4: STRINGSET DAN HV CONNECTOR | F4: Sudah PO untuk DP dibayar per GI, kontraktor mengajukan adendum untuk perpanjangan kontrak, PO Connector sudah, blm ada progres dari kontraktor. Akan membayar lagi bulan Juni | H4: FU Fuad, sudah ada approval drawing dari kontraktor, PO kontraktor sudah diterima, Invoice sudah dibuatkan tgl 2 April 2020 | I4: 120 FOG, 700 PCS | J4: approval drawing untuk connector dan string set sudah ada, AR nya 400, kontrak sudah lewat, belum ada update lagi | K4: Fuad | L4: 1. PO Stringset Purwodadi (DP Purwodadi 78 Juta sisa 182 juta). 2. PO Stringset Balapulang (Done) 3. PO Stringset Kesugihan (Done) 4. PO Connector Balapulang (Done) PO add belum lunas 5. PO Connector Kesugihan (Done)
A5: 3 | B5: GI 150 kV Air Raja | C5: K E | D5: STRINGSET DAN HV CONNECTOR | F5: dokumen penagihan sudah lengkap di Bag. Keuangan KE (0254) 394100 ext 144 (PIC. Pak Yapi) | G5: sudah dikirim | J5: Bag. Keuangan Kasih list AR KE ke pak aco | K5: Fuad | L5: - air raja dan add malimping tertunggak 860 juta dicicil selama 10 bulan (perbulan 86juta) - cicilan bulan mei 2021 sudah di bayar (75jt)
A6: 4 | B6: TL 150 kV Malimping Bayah | C6: K E | D6: Stringset & Ubolt | F6: dokumen penagihan sudah lengkap di Bag. Keuangan KE (0254) 394100 ext 144 (PIC. Pak Yapi) | G6: Sudah dikirim | J6: Bag. Keuangan Kasih list AR KE ke pak aco | K6: Fuad | L6: - retensi Rp.382.596.613, maret bayar Rp.267.116.372 sisa Rp.115.453.241 2021 - cicilan bulan mei 2021 sudah di bayar (75 jt)
A7: 5 | B7: Bay Kapasitor GI Tersebar | C7: KSO TDKK - Metrindo | D7: Stringset | L7: - belum bayar 258 juta (final qty belum selesai) - menunggu final cek dari PLN, di FU oleh Pak Samudra
A8: 6 | B8: TL Cisumdawu | C8: DSU | D8: Stringset | L8: - belum bayar 432 juta
A9: 7 | B9: GI Rum | C9: Pratama Tunas Nusantara | L9: - belum bayar 462 juta
A10: 8 | B10: GI 150 kV Sekotong | C10: Sastramas | D10: STRINGSET DAN HV CONNECTOR | F10: PLN sudah Approval, PO kontraktor sudah, invoice DP di bulan maret 2020, | G10: PLP sudah kirim AO due tgl 7 april 2020 | H10: Sudah PO | J10: Barang sudah diambil semua | K10: Fuad | L10: - sisa hutang nya 740 juta baru dicicil 1x (50juta)
A11: 9 | B11: GI Padang Sambian | C11: Sastramas | D11: STRINGSET DAN HV CONNECTOR | J11: Barang sudah diambil semua | K11: Fuad | L11: - belum bayar 273 juta janji habis lebaran, 17 Mei 2021
A12: 10 | B12: GI Ende Ruteng | C12: Sastramas | J12: Barang sudah diambil semua | K12: Fuad | L12: - belum bayar 82 juta
A13: 11 | B13: Komponen HWK App Purwokerto | C13: Pelita Bumi Wangi | D13: Komponen HWK | F13: *. Pembayaran di bulan maret 2020 tgl 10 maret jika blm ada akan memberikan giro | H13: FU pak Fuad | I13: - | K13: Fuad | L13: - kurang 101 juta Janji dibayar habis lebaran 17 Mei 2021
A14: 12 | B14: Sangata Maloy Sec. 1-3 | C14: Waskita Karya | D14: Stringset | E14: 16 Maret 2021 | K14: Bu Sari | L14: - Material tahap 1 sudah di kirimkan, Surat Delivery Time sudah diberikan dari PLP - material add akan dikirim bulan juni - addendum kontrak ttd waskita sudah diterima - cicilan sec.1 sudah dibayar 500jt bulan mei 2021
A15: 13 | B15: Relokasi KCIC DK 73 | C15: Dwipa Konektra | H15: Sudah PO Stringset ke PLP DK 73, Insulator belum PO menunggu approval dari WIKA | K15: Priyo | L15: menunggu pembayaran pelunasan dari dwipa dan pengambilan material nya
A16: 14 | B16: TL 150 KV Rengat Tembilahan 4 | C16: PT. Waskita Karya | D16: Stringset | H16: Pengiriman untuk material tgl 15 Oktober sudah dikirim | K16: Priyo | L16: - Barang add sudah dipacking - cicilan sudah dibayar 500jt
A17: 15 | B17: GI Manisrejo | C17: Purnama | D17: Stringset & Connector | K17: Priyo | L17: - Barang sudah digudang - DP belum (201 juta pelunasan 470 juta) - pembayaran giro jatuh tempo 22 Juni 2021 - cicilan pembayaran 50 jt bulan Mei 2021
A18: 16 | B18: Post Insulator 20kV | C18: Basuki | D18: Post Insulator | L18: - maret sudah bayar 200jt sisa 87jt
A19: 17 | J19: 83-866-054-458
A20: 18
C21: Very Urgent
C22: Urgent
C23: Standart

Sheet Next Project
B1: Next Project
A2: No | B2: No | C2: Project Name | D2: Desc | E2: Estimated Value (Rp) | F2: Kontraktor | G2: PIC | H2: Remark | I2: Target | J2: Keterangan
B3: 1
B4: 2
A5: 26 | B5: 3
A6: 27 | B6: 4
B7: 5
B8: 6
B9: 7
B10: 8
B11: 9
B12: 10
B13: 11
B14: 12
B15: 13
B16: 14
B17: 15
B18: 16
... B29: 27

Sheet Loss
A2: Project Loss
A4: No | B4: Project Name | C4: Nama Kontraktor | D4: Desc | E4: PLP Promise | F4: Remark Kontraktor | G4: Remak PLP | H4: Remarks | I4: PIC
A5: 1 | B5: GI 150 kV SUNYARAGI | C5: MPT | D5: DISC INSULATOR | E5: End of Desember 2019 | F5: Sudah ada penawaran dari Alam, diganti sediver | G5: - | H5: 120 FOG, 1250 PCS Menunggu Konfirmasi dari Pak Dyan | I5: Priyo
A6: 2 | B6: GI 150 kV SEMEN JAWA | C6: MPT | D6: STRINGSET DAN HV CONNECTOR | E6: End of Desember 2019 | F6: Menunggu penawaran dari Alam | G6: Tunggu penawaran dari PLP | H6: GANTI MEREK, Karena kita minta penawaran 24 april baru di berkan harga 9 juni | I6: Priyo
A7: 3 | B7: Relokasi 275 kv Pekanbaru | C7: Bekasap | D7: Stringset | F7: Menunggu Penawaran dari Alam (Priyo) FU pak priyo tgl 25/11/2019 | I7: Priyo
A8: 4 | B8: CISUMDAWU PHASE 4 | C8: CMS/DSU (Dede Sufthendy) | D8: STRINGSET ACSR 450/410 | F8: batal PO, email sudah , menunggu pembayaran 420 juta | H8: kebutuhan material : double tension yang kita punya 340, 450 (12 set) Insulator 300 pcs, Light weight spacer 200 crs for ACSR 450 15 pcs, dan spacer 400 crs ACSR 450 42 pcs koordinasi untuk leadtime kabelindo dan penambahan material outstrisd dan ACSR 120 material stok ACSR 340 tetapi harus diganti untuk double conductor menjadi single | I8: Aco
A9: 5 | B9: GI 150 kV SUMENEP | C9: PPWS | D9: STRINGSET DAN HV CONNECTOR | E9: End of Maret 2019 | F9: pak aco udh FU untuk pembayarannya karena copy invoice sudah di serahkan | H9: connector memakai produk lokal tidak PLP String dan konektor masih menunggu dari PLP (Drawing dan Penawaran) | I9: Aco
A10: 6 | B10: 150KV GI PAMEKASAN | C10: PPWS | D10: Connector | E10: Agustus 2019 | F10: hanya beli string set nya selesai, spacer blm bikin PO | H10: spacer masih ditanyakan ke pak dede, Crossceck PO terdahulu di keuangan Konektor masih menunggu konfirmasi Pak Dyan, belum di PO Konektor | I10: Aco
A11: 7 | B11: GI Balaraja | C11: GTS | D11: Stingset | F11: blm di approval jadi blm di bikin PO (blm ada Update) pak fuad FU minggu ini | H11: Pak Fuad FU minggu ini | I11: Fuad
A12: 8 | B12: GI Lengkong, GI Legok | D12: Stringset dan Conector | F12: Tender di ulang habis lebaran | G12: Menunggu Shoping list dari kontraktor | H12: menunggu meeting dgn PLP, hasilnya untuk meeting tgl 10 Maret 2020 di PLN Gandul Kontraktor belum kontrak dengan PLN, FU pak priyo ke pak wahyu | I12: Priyo
A13: 9 | B13: GI Tanjung Pura 150kV dan GI Samalanga | C13: Medan Smart Jaya | D13: ADSS+Join Box | G13: AO Sudah | H13: Barang sudah jadi, invoice dikirim 25 Februari 2020 | I13: Aco
A14: 10 | B14: Sorikmarapi | C14: Lumintu - Supraco | H14: Menunggu konfirmasi dari kontraktor, hari ini ada info dari Lumintu pak dunung | I14: Priyo
A15: 11 | B15: Proyek 150KV ACCC Kopenhagen Relokasi Tower KCIC | C15: EIP | H15: Harga Terlalu Mahal | I15: Aco
A16: 12 | B16: Kontraktor Cirebon | C16: PT Cipta Daya Utama | G16: Penawaran sudah tunggu PO | H16: Survei tgl 30 Juni 2020 | I16: Priyo
A17: 13 | B17: SUTT Wonosobo Secang, SUTT Jelok - Sanggrahan | C17: Stringset dan Insulator | D17: 3600000000 | E17: UPT Salatiga | F17: Priyo | G17: Pemenang Pelita Bumi Wangi
A18: 14 | B18: TL 150 Marisa - Moutong Sec.1&2 | C18: Stringset Insulator | E18: PT. KAP | F18: Priyo | G18: Dokumen kelengkapan tender sudah diberikan
A19: 15 | B19: Nusra 7 TL 5 GI | C19: Stringset Insulator | D19: 2200000000 | E19: KAP | F19: Priyo & Aco | G19: GI Bima Sape Lanjutan(KAP) kalah | H19: 44202 | I19: Ditunda Thn Depan
A20: 16 | B20: Relokasi KCIC DK 86 | E20: Dwipa | G20: Dwipa ke KPP
A21: 17 | B21: TL 150kV Tanjung Sari | E21: Alhas Jaya Group | F21: Priyo
A22: 18 | B22: GISTET Duri Kosambi 500kV dan GI 150kV Duri Kosambi | E22: PT Buana Reksa | F22: Fuad | G22: Pemenang Buanareksa pakai sicam | H22: 44202
A23: 19 | B23: TL 150kV Marunda Bekasi | C23: Tri Sinergi | H23: pake barang KAK (ready) | I23: Priyo
A24: 20 | B24: GIS 150 kV Ancol | C24: STRINGSET DAN HV CONNECTOR | E24: Lumintu | F24: Priyo | G24: dibatalkan sepihak oleh PLN
A25: 6 | B25: KCIC DK108 atau SUTT 150KV Purwakarta - Kosambi Baru Tol Japek 2 Sisi | C25: CMS | F25: Pemenang PT. CMS, menunggu pembayaran dari WIKA | H25: Menunggu info dari pak asep CMS, lahan belum bebas ditunda atau kemungkinan dibatalkan | I25: Fuad
A26: 8 | B26: Jatiluhur - Cikampek DK 130 & 132 | C26: Alhas | D26: Stringset & Insulator ( Dalian) | F26: menunggu approval drawing dari PLN E, PLN UIT Bandung | H26: - menunggu info konsinyering dari KCIC dan UIP Bandung, menunggu approval PLN E | I26: Fuad
A27: 8 | B27: Pengadaan dan Pemasangan MTU P0 Non Swakelola di UPT Gresik tahun 2021 | C27: 100000000 | D27: Menunggu Eksekusi Project | E27: PT MULYA JATRA | F27: HVC | H27: PLP/Sicame
A28: 12 | B28: Penggantian MTU KARAWANG | C28: 100000000 | D28: Loss, Balik ke IAG | E28: PT JATIMULIA INDONESIA | F28: HVC
A29: 7 | B29: PEMBANGUNAN BUS SECTION GI 150KV PAITON | C29: 100000000 | D29: Menunggu Eksekusi Project | E29: PT MULYA JATRA | F29: HVC | H29: info ke PLN | J29: menunggu revisi Drawing dari PLP
A30: 23 | B30: PENGGANTIAN KAWAT GSW SUTET 500 KV BALARAJA – LENGKONG – GANDUL DALAM RANGKA PENGGANTIAN GSW TERSEBAR PADA SALURAN TRANSMISI WILAYAH UPT CAWANG | D30: Menunggu kontrak | E30: Karya Putra Gemilang, PT | N30: KSO dengan Bira, Kemungkinan besar Bira sudah opeb PO ke distributor lain
A31: 24 | B31: PENGGANTIAN TRAFO KONDISI KRITIS PO TRAFO 2 70/20 KV GI KRACAK | C31: 50000000 | D31: Menunggu Kontrak | E31: INDEVCO GLOBAL, PT | J31: FU
A32: 9 | B32: JASA PENGGESERAN TRAFO DI GI 150KV BANARAN, GIS DRIYOREJO DAN GI 70KV DOLOPO (PEKERJAAN UPRATING IBT 1 DAN TINDAKLANJUT ANOMALI PENGGANTIAN TRAFO 4 GIS DRIYOREJO | C32: 24754900 | D32: Menunggu konfirmasi kontraktor | E32: Karyasembada Ciptamandiri, PT | J32: Kontraktor menunggu konfirmasi PLN terkait kesiapan material 6 minggu, Mbak Laely cari barang yang stock
A33: 14 | B33: PENYEMPURNAAN REKONFIGURASI SINGLE BUSBAR MENJADI DOUBLE BUSBAR GI BULUKANDANG (TAHAP 2) | C33: 300000000 | D33: Menunggu kontrak | E33: Kencana Alam Putra, PT | F33: String set & Insulator 120Fog | J33: Material pakai pabrikan sangdong
A34: 24 | B34: Insulator U120BP | C34: 5241100000 | E34: PT Alhas Jaya Group | L34: Minta dari negara OECD, minta penawaran harga ke La Granja | M34: Mbak Laely
A35: 6 | B35: SUTT PLN UPT BEKASI | E35: Jati Mulia, PT - DUTA CAKRAWALA INDONESIA, PT | J35: FU ke kontraktor penawaran harga alam,Jati Mulia belum dibalas ,DCI Mundur | L35: Fu nabil minggu ini | M35: Mbak Laely
A36: 28 | B36: Pengadaan Barang dan Jasa Konstruksi SUTT 150 kV Kubu – Amlapura Section 1 | C36: 2000000000 | E36: KSO CITRA RIANTARA - ALHAS JAYA GROUP, PT | J36: FU ganti ke Euis, Tidak jadi ikut karena HPS terlalu rendah
A37: 30 | B37: Pengadaan Barang dan Jasa Konstruksi SUTT 150 kV Kubu – Amlapura Section 3 | C37: 2000000000 | E37: KSO MAHAKAAM - ALHAS JAYA GROUP, PT | J37: FU ganti ke Euis, Tidak jadi ikut karena HPS terlalu rendah
A38: 39 | B38: Kabel Dropwire 2 & 4 Core | E38: Moratelindo,PT | I38: CCSI | M38: Pak Agus
A39: 14 | B39: Tender Material Non Rutin UPT Duri Kosambi | C39: 3303962991 | E39: PLN UPT Duri Kosambi, PT | J39: Pemenang tender SPE | M39: Dita
A40: 22 | B40: Jasa Pekerjaan Perbaikan Anomali Instalasi & tindak lanjut gangguan di UPT Bogor | C40: 1420000000 | E40: PLN UPT Bogor, PT | J40: Kalah tender, Pemenang PSE, INA missed di PPN | L40: closing 27 Januari 2023
A41: 26 | B41: Jasa Penggantian GSW korosif dan stringset pada SUTET 500 kv Cirata-Deltamas 2 span UPT Karawang | C41: 1674888000 | E41: PLN UPT Karawang, PT | J41: Pemenang tender PT. Arca | L41: closing 6 Februari 2023
A42: 27 | B42: Pembangunan GI 150 kV Pematang Siantar (Ext.) 2 LB Arah Tanah Jawa | C42: 400000000 | E42: Sapta Guna Utama, PT | J42: Pemenang PT. Elsewedy | L42: closing 23 January 2023
A43: 26 | B43: Pembangunan GI 150 kV Pematang Siantar (Ext.) 2 LB Arah Tanah Jawa | C43: 400000000 | E43: Sibrama Sakti, PT | J43: Pemenang tender PT. Elsewedy | L43: closing 23 January 2023
A44: 27 | B44: Pembangunan GI 150 kV Pematang Siantar (Ext.) 2 LB Arah Tanah Jawa | C44: 400000000 | E44: Sibrama Sakti, PT | J44: Pemenang tender PT. Elsewedy | L44: closing 23 January 2023
A45: 29 | B45: Pengadaan Barang dan Jasa Konstruksi SUTT 150 kV Kubu – Amlapura Section 2 | C45: 2000000000 | E45: ALHAS JAYA GROUP, PT | J45: Pemenang tender PT. Indisi
A46: 31 | B46: Pengadaan Barang dan Jasa Konstruksi SUTT 150 kV Kubu – Amlapura Section 2 | C46: 2000000000 | E46: Hasta, PT | J46: Pemenang tender PT. Indisi
A47: 37 | B47: Clamp MTU UPT Duri Kosambi | C47: 23000000 | E47: Duta Cakrawala Indonesia ,PT | J47: Karena respon PLP lama, Kontraktor minta ke SDR
A48: 40 | B48: Insulator Glass 1700 pcs untuk 500kV (160/210kN Fog ,GIG) | E48: UPT PLN BEKASI/BOGOR,PT | J48: FU Mbak Laely
A49: 13 | B49: Insulator Polymer UPT Pulogadung | C49: 15000000000 | E49: PLN UPT Pulogadung, PT | H49: Tidak lolos sampul 1 karena tidak ada surat keterangan kepuasan pelanggan dari pekerjaan barang dan jasa | M49: Mbak Laely
A50: 18 | B50: Kabel NYRGbY 4x10 mm | C50: 93200000 | E50: PT Arca Energi | H50: Harga terlalu mahal | M50: Mbak Laely
A51: 19 | B51: Insulator Dalian | C51: 52286400 | E51: PT Arca Energi | M51: Mbak Laely
A52: 22 | B52: Jasa penggantian stringset serta Insulator SUTT 70kV Cibinong Cileungsi | C52: 500000000 | E52: PLN UPT Bogor, PT | H52: INA missed di PPN, Ada 6 yg ikut, pemenang sampul 1 Pelita bumi wangi, DCI, Cita yasa, yang pemenang harganya Pelita bumi wangi | L52: closing 27 Januari 2023
A53: 20 | B53: Relokasi SKTM Jl.Narogong (voksel) | C53: 9124500000 | E53: PT Sigeaon Indah Mandiri | H53: Minta ganti spek sesuai dengan SPLN, kontraktor pakai product voksel FU Mbak laely tanggal 27 Maret 2023 | L53: 45017 | M53: Mbak Laely
A54: 26 | B54: GI 150kV Semen Jawa | C54: 12000000 | E54: Mega Power Teknindo, PT | H54: FU Euis terakhir tgl 20 Jan 2023 dan FU lagi 6 Maret 2023
A55: 30 | B55: Dead end dan Jumper | E55: PPN,PT | J55: FU Mbak Laely, kasih drawing kita, pak dedy cek stock gudang
A56: 31 | B56: Pengadaan Barang dan Jasa Konstruksi GI 150 kV Amlapura Extention 2 Line Bay | E56: Purnama Indonesia, PT | J56: Pemenang Tender Mega Power
A57: 25 | B57: Pengadaan Barang dan Jasa Konstruksi GI 150 kV Amlapura Extention 2 Line Bay | C57: =715537600+356584000 -> 1072121600 | E57: Mega Power Teknindo, PT | H57: Pemenang tender, Mega power dikarenakan penawaran harga lebih murah Alam
A58: 35 | B58: Jasa penanganan anomali dan tindak lanjut gangguan transmisi wilayah upt purwokerto maret tahun 2023 - februari 2024 | C58: 1517000000 | E58: PLN Purwokerto | H58: Kita gagal sampul 1 dikarenakan gagal di bidbond, Pemenang tender simbarhol Closing 6 Maret 2023
A59: 36 | B59: JASA PENGGANTIAN KAWAT GSW BERIKUT STRINGSETNYA DI SPAN T.1 – T.26 SUTT 70 KV PURWAKARTA – INDORAMA #1 DAN #2 DAN SPAN T.1 – T.30 SUTT 150 KV JATILUHUR – TATAJABAR #1 | E59: Hydro Techno Utama, PT | H59: Missed ALAM tidak memberikan TPG, Pemenang tender Arca Energi
A60: 10 | B60: Penggantian Stringset di wilayah UPT Pulogadung | C60: 6000000000 | E60: PLN UPT Pulogadung, PT | J60: Tender baru akan dikeluarkan bulan april, 27 Maret 2023 Ilham FU ke Pak Guntur | L60: Kebutuhan untuk April 2023- April 2024 | M60: Mbak Laely
A61: 22 | B61: Additional Supply MTR 5 from MTR 2 | C61: 1999689000 | E61: Indonesia Asahan Alumunium,PT | J61: Kalah Tender
A62: 17 | B62: Pemindahan Tower 150kV Cilegon | C62: 12821163700 | E62: Krakatau Daya Listrik, PT | J62: Tender Gagal
A63: 18 | B63: PENGADAAN DAN PEMASANGAN BUSHING TERSIER PHASA R, T BAY IBT 1 500/150 KV GITET BANDUNG SELATAN, BUSHING PHASA N BAY TRAFO 2 150/20KV GI PADALARAN BARU, BUSHING NETRAL LV BAY IBT 1 150/70 KV GI CIGERELENG, BUSHING PHASA R BAY 4R2 GITET BANDUNG SELATAN, BUSHING PHASA S BAY IBT 1 GI UJUNGBERUNG, BUSHING PHASA R,S,T BAY TRAFO 4 GI RANCAEKEK DAN BUSHING PHASA T BAY TRAFO 1 GI NEW RANCAKASUMBA | C63: 16618600 | E63: PT. Lembah Sentral Elektronindo | J63: Retender, pemenang tender PT. ENINDO ORBITAMA
A64: 21 | B64: PENGADAAN ISOLATOR POLIMER 210KN BESERTA STRINGSET DAN JASA PENGGANTIAN DI SUTET 500 KV ADIPALA-S2P 1,2 T.8-10, SUTET 500 KV PEDAN-KESUGIHAN 1,2 | C64: 1048280200 | E64: Mega Alfarizki, PT | J64: Kalah pemenang pandan wangi pakai huble, mega alfarizki pakai fister
A65: 25 | B65: Pembangunan Extension 2 LB GI 150kV Kariangau arah GIS 4 IKN dan Site Development GIS 4 IKN | C65: 231318300 | E65: PT. DISTRACO | J65: Kalah, pemenang tender jampa, esweldy, sejahtera
A66: 26 | B66: PENINGGIAN TOWER T.54 DAN T.55 SUTT 150 KV CHANDRA ASRI – ANYER | C66: 33415200 | E66: PT DUTA CAKRAWALA INDONESIA | J66: Gagal karna harga diatas HPS
A67: 27 | B67: PEKERJAAN PEMBANGUNAN EXTENSION 2 LINE BAY GI 150kV KARIANGAU ARAH GIS 4 IKN | C67: 933000 | E67: PT.Indokomas Buana Perkasa | K67: 660
A68: 35 | B68: JASA PENGGANTIAN KABEL POWER 20 KV 2 GI TELUKJAMBE | C68: 403275000 | E68: Prima Power Parahiyangan, PT | J68: Lulus sampul 1, kalah harga dari jabar jaya Jabar jaya; 698 Prima Power; 732 HPSnya 775
A69: 32 | B69: DESAIN, SUPLAI DAN PEMASANGAN GIS 4 IKN | C69: 89258400 | E69: KSO PT. CEMERLANG SAMUDRA KONTRINDO - PT. High Volt Technology | J69: Penawaran harga sudah dikirim
A70: 17 | B70: Pengadaan Barang dan Jasa Konstruksi GI 150 kV Amlapura Extention 2 Line Bay | C70: =660000000+270000000 -> 930000000 | E70: Mega Power ,PT | J70: Pemenang tender Mega Power, pakainya sangdong dan dalian
A71: 19 | B71: PENORMALAN KONFIGURASI DOUBLE PHI SUTT 150 KV BEKASI – PENGGILINGAN – RAWA TERATE DI GIS PENGGILINGAN | C71: 89122300 | F71: PT MULYA JATRA | K71: Pemenang Guna swastika dinamika
A72: 24 | B72: PENGGANTIAN SEALING END INDOOR DAN OUTDOOR DI WILAYAH UIT JBB LINGKUP PENGGANTIAN SEALING END JENIS XLPE | C72: 38471700 | F72: Indevco Global, PT | K72: Closing tgl 15 Mei 2023, Tidak jadi ikut pemasukan dikarenakan tidak ada dukungan sealing end
A73: 25 | B73: JASA PENGGANTIAN MTU P0 DI WILAYAH UPT PURWOKERTO | C73: 198548700 | F73: Lembah Sentral Elektronindo, PT | K73: Selasa, tgl 16 Mei 2023 pembukaan sampul 2 sudah kemarin hari jumat & LSE kalah di harga selisi 128jt-an
A74: 21 | B74: PENGGANTIAN DAN PENYEMPURNAAN PERALATAN INSTALASI GARDU INDUK DI WILAYAH UIT JBB LINGKUP JASA PENGGANTIAN TRAFO #3 150/20 KV 60 MVA GIS GEDUNG POLA | C74: 14982300 | F74: Indevco Global, PT | K74: Tender batal type test diminta 2000amper tetapi yang diberikan 1600amper peserta simbarhol, Electrika mitra usaha PLN Pulogadung
A75: 22 | B75: REROUTETOWER 26 SUTT 150KV BALOI – TJ. SENGKUANG | C75: 353792000 | F75: KSO PT Tesla Daya Elektrika Dan PT. Citra Riantara Sejahtera | K75: Kalah 200jt dari Buanareksa, pemenang tender pakai sicame, Trimitra sudah sepaket dengan insulator
A76: 20 | B76: PENGADAAN DAN PEMASANGAN KAPASITOR DI GI 150KV PAKIS (PENGADAAN DAN PEMASANGAN KAPASITOR DI GI 150KV PAKIS) | C76: =575084800+562345200 -> 1137430000 | F76: Purnama Indonesia, Indevco Global, Buanareksa BinaPerkasa, PT | K76: Pemenang tender Hasta Karya
A77: 22 | B77: PEMBANGUNAN TRANSMISI 275 KV ARUN – SIGLI SEKSI 1,2,3,4 | E77: SGU dan Kembar Abadi Sangkan belum dapat pasangan QDC belum dapat pasangan Bugak dan Twink LNT sudah ok Medan smart dan BBS (Senin ke Twink Selasa ke Rekadaya, citramas, Multifab) | F77: Bukaka SGU Indisi Kembar Abadi BBS Reka Daya Sangkan Citramas Persi Bugak QDC Medan smart LNT Siticon Twink Multifab | K77: Closing tgl 17 Juli 2023
A78: 24 | B78: DESAIN, SUPLAI DAN PEMASANGAN TRANSMISI 500 KV PAITON – KALIPURO SEKSI 2 | C78: =12062620570+2614614324 -> 14677234894 | F78: PT. Larsen and Toubro | K78: Closing tender 13 Juli 2023
A79: 25 | B79: PENGGANTIAN TRAFO TERSEBAR DI WILAYAH UNIT INDUK TRANSMISI JAWA BAGIAN TENGAH | C79: 113314100 | F79: PT. Lembah Sentral Elektronindo | K79: Tidak lolos sampul 1 karena admin
A80: 27 | B80: PENGADAAN DAN PEMASANGAN TLA DI WILAYAH UNIT INDUK TRANSMISI JAWA BAGIAN TENGAH | F80: PT MEGA ALFARIZKI | K80: Closing tanggal 12 Juni 2023, Menunggu Penawaran harga dari sicame Indokarya=9M(buang 26%) Mega Alfa=10M(buang 16%) Pandan Wangi=17M. Pagu 12M
A81: 29 | B81: PENGGANTIAN KABEL POWER DI WILAYAH UPT DURIKOSAMBI UIT JBB TAHUN 2023 | C81: 46128000 | F81: PT. INDEVCO GLOBAL | K81: Pemenang tender DCI
A82: 15 | B82: EPC SUBSTATION UPGRADE WK ROKAN | C82: 250578300 | F82: Mahakaam Jaya Sejahtera, PT | K82: Bukan ke PLN, Insulator porcelain dan konduktor, permintaan ke, INA & ALAM, Rabu 31 Mei 2023 Kekurangan ina string set 150kV, belum ada info untuk kelanjutan, kemarin baru dapat info mengenai progres sekar putih yg kemungkinan akan kami dapatkan, pemenang : rekadaya elektrika
A83: 18 | B83: PENGGANTIAN SEALING END INDOOR DAN OUTDOOR DI WILAYAH UIT JBB LINGKUP PENGGANTIAN SEALING END JENIS XLPE | C83: 38471700 | F83: High Volt Technology, PT | K83: Masih evaluasi teknik, FU Ikhbal 3 Juli 2023, tidak lolos sampul 1, yang lolos indo karya
A85: 19 | B85: PEMASANGAN PROTECSI PETIR TOWER DI UPT PEKAN BARU | F85: PT PERSADA INDAH MUDA | K85: Kalah karena tidak ada end usernya di jasa
A86: 20 | B86: PENGADAAN DAN PENGGANTIAN ISOLATOR POLIMER ULTG TERSEBAR | C86: 1765861500 | F86: KONSORSIUM PT. ANDEKJA PUTRA – PT. KELINCI MAS UNGGUL | K86: Pemenang tender Kelinci Mas, Harga biding 1,4M jadi tidak pakai harga kita
A87: 29 | B87: PENGADAAN ISOLATOR TRANSMISI UIP3B KALIMANTAN | C87: 1138669700 | E87: Kalimantan | F87: Persada Indah Muda,Maha Daya, Iradat, Amperatech Solusindo Global,PT | I87: closing 14 Juli 2023, masih evaluasi | K87: Closing tanggal 10 Juli 2023, Drawing, Sudah pembukaan sampul 2 harga terendah iradat, pemenang iradat buang 12% pagu 2,2 masukin harga 1,936M termasuk PPN
A88: 30 | B88: PENGAMANAN TRAFO DARI GANGGUAN BINATANG DI WILAYAH UPT PROBOLINGGO | F88: INA,PIM,KSCM,Citra Riantara,PT | I88: nilainya : 2,4M, bid bond 1%, dukungan bank 10% | K88: Closing tanggal 26 Juli 2023, Aanwijzing 12 Juli 2023
A89: 9 | B89: Rekonduktoring Transmisi Garung Wonosobo | C89: 7675445460 | F89: Krakatau Daya Listrik, PT | K89: Info dari KDL belum ada kejelasan infonnya akan diserahkan ke PLN dan info dari PLN asetnya ke Geodipa Cek UIP JBT pak Djarot, FU Elektra Mega Mandiri, Mbak Laely cek ULTG Wonosobo, Rabu visit ke KDL 26 Juli 2023, Bukan KDL yang mengerjakan
A90: 10 | B90: Pengadaan dan Pemasangan JUTM | C90: 597489768 | F90: Krakatau Daya Listrik, PT | K90: Penawaran harga sudah dikirim, pekerjaan kemungkinan Q3 tahun ini Mbak Laely FU ke pak Tur, Projectnya tidak disetujui direksi di print brosure yang baru
A91: 32 | B91: PENGADAAN DRONE SISTEM TRANSMISI | C91: 2067646839 | E91: Elekrika, Gapeksindo jaya bersama, Spektrum krisindo elektrika, stal elektrika, INA | I91: nilainya : 2,1M, tidak pakai bid bond, dukungan bank 220jt, closing 21 Juli 2023 | K91: Closing tanggal 21 Juli 2023, Aanwijzing 7 Juli 2023, BA sudah keluar, Tidak Lulus Sampul 1 yang lulus spektrum dan stal elektrika
A92: 15 | B92: PENGADAAN PEMBANGUNAN BAY TRAFO 60 MVA | F92: PT. HVT,Buanareksa,LSE,Sibrama Teknik, NSU | K92: 1. WST 2. Buanareksa 3. Ahza
A93: 26 | B93: PENGADAAN ISOLATOR TRANSMISI UIP3B KALIMANTAN | F93: Persada Indah Muda,PT | K93: Lulus sampul 1, Iradat pemenang (1.935.000.000 sudah include PPN jadi buang 21%)
A94: 38 | B94: PEMBANGUNAN BAY KAPASITOR 1X25 MVAR SISTEM INTERKONEKSI | F94: Lembah Sentral Elektronindo,PT | K94: Closing 2 Agustus 2023
A95: 34 | B95: Pemasangan proteksi petir tower di UPT Jambi | C95: 642842200 | F95: Tesla Daya Elektrika,PT | K95: Closing 31 Juli 2023, tidak jadi pemasukan tidak punya laporan keuangan 2022
A96: 30 | B96: PENGADAAN DAN PEMASANGAN BAY KAPASITOR 2 X 25 MVAR DI UPT KALTIM | C96: =324795200+226476000 -> 551271200 | F96: Lembah Sentral Elektronindo,PT | I96: Gugur di TPG | K96: Closing 2 Agustus 2023
A97: 31 | B97: PENGADAAN DAN PEMBANGUNAN BAY KAPASITOR 2 X 25 MVAR GI TERSAMBUNG PELANGGAN KTT | C97: =226476000+389795700 -> 616271700 | F97: KSO PT. Lembah Sentral Elektronindo – PT. Arlisco Elektrika Perkasa | I97: Gugur di TPG | K97: Closing 2 Agustus 2023
A98: 32 | B98: PENGADAAN DAN PEMBANGUNAN BAY KAPASITOR 2 X 25 MVAR GI TERSAMBUNG PELANGGAN KTT | C98: =381386400+223365600 -> 604752000 | F98: Distraco,PT | I98: Kalah di auction, pemenang indokomas | K98: Closing 2 Agustus 2023
A99: 28 | B99: PENGADAAN DAN PEMASANGAN BAY KAPASITOR 2 X 25 MVAR DI UPT KALTIM | C99: =308899400+223365600 -> 532265000 | F99: Distraco,PT | I99: Closing tgl 2 Agustus 2023 | K99: Closing 2 Agustus 2023, Kalah sampul 2, Pemenang tender PT PERSADA ENGINEERING & CONTRACTING Nilai peroleh Rp.26.129.400.000,00
A100: 29 | B100: PEMBANGUNAN BAY KAPASITOR 1X25 MVAR SISTEM INTERKONEKSI | C100: =111553400+37227600 -> 148781000 | F100: Distraco,PT | I100: Closing tgl 2 Agustus 2023 | K100: Closing 2 Agustus 2023, Kalah sampul 2, Pemenang tender PT PERSADA ENGINEERING & CONTRACTING Rp.12.330.000.000,00
A101: 30 | B101: UPRATING KONDUKTOR MTU DI GI 150KV SITUBONDO DAN GI 150KV BANYUWANGI | F101: PT. CAHAYA KARYA BERSAMA | I101: Closing tgl 24 Agustus 2023 | K101: Closing 24 Agustus 2023, klarifikasi sampul 1, pemenang tender mega jaya sukss utama
A102: 32 | B102: UPRATING KONDUKTOR MTU DI GI 150KV SITUBONDO DAN GI 150KV BANYUWANGI | F102: Persada Indah Muda,PT | I102: Closing tgl 24 Agustus 2023 | K102: Closing 24 Agustus 2023, klarifikasi sampul 1, pemenang tender mega jaya sukss utama
A103: 31 | B103: PERBAIKAN PENTANAHAN BERNILAI BURUK SUTET/SUTT DI UPT PROBOLINGGO | F103: PT. CAHAYA KARYA BERSAMA,PIM | I103: Closing tgl 15 Agustus 2023 | K103: Pemenang tender PIM pakai KAK
...

Sheet LATEST LOSS
A1: No | B1: Project Name | C1: Value excl. PPN | D1: Status | F1: CUSTOMER | G1: Desc | H1: Factory Promise | I1: Remarks Kontraktor | J1: Remarks Principle | K1: Remarks AI | L1: INSULATOR | M1: Remarks | N1: PIC | O1: Keterangan
A2: 29 | B2: PEMBANGUNAN GI 150/20 KV SOREK DAN INCOMER SUTT 150 KV | C2: =1494960280+618749219 -> 2113709499 | D2: 113000000000 | E2: pakai handal & hogn minta harga mereka | F2: PT. Sapta Guna Utama | K2: Closing tgl 27 Agustus, FU Ibu 9 sept (3 merk), pakai handal & hogn minta harga mereka
A3: 51 | B3: Pengadaan Alat Thermovisi GI Tersebar di UPT Bekasi | F3: PT. Indodaya Naratama Abadi | K3: Tidak submit, harga Flir tidak masuk HPS
A4: 52 | B4: Pengadaan dan Jasa Penggantian String Set serta Isolator untuk SUTT 70 kV Kedung Badak - Kracak Tahap 3 | F4: PT. Indodaya Naratama Abadi | K4: tidak lulus sampul 1, karna dok teknis data supply dari pabrikan & kontrak dan data personalia dan CV Pemenang spektrum 475 harga kita 503
A5: 53 | B5: Pengadaan dan Jasa Penggantian String Set serta Isolator untuk SUTT 70 kV Kedung Badak - Kracak Tahap 3 | F5: PT. Tuban Jaya Mandiri | K5: Closing 21 Nov (minta isolator Huble) kalah sampul 2
A6: 14 | B6: PENGADAAN ALAT UJI DI WILAYAH UPT BANDUNG | D6: HPS: 955.955.925 | F6: PT. INDODAYA NARATAMA ABADI | K6: Aanwijzing 19 des closing 15 January 25
A7: 36 | B7: Pekerjaan Pembangunan Extension 1 Trafo Bay + Trafo 30 MVA Gardu Induk 150 kV Satui | F7: PT. MEGA POWER TEKNINDO | K7: Closing 6 Desember, kalah sampul 1
A8: 38 | B8: PENGGANTIAN STRINGSET DAN ISOLATOR SUTT 150 KV JATILUHUR – PADALARANG TAHAP 1 | F8: PT. TUBAN JAYA MANDIRI, PT MEGA ALFARIZKI | K8: Mega alfa kalah sampul 2 , tuban tidak masukin penawaran
A9: 28 | B9: PENGADAAN DAN PENGGANTIAN MTU DI WILAYAH UPT SEMARANG | C9: 6011000000 | D9: Masatek
A10: 29 | B10: JASA PELAKSANAAN UPRATING BAY TRAFO GI 150 KV KE 2 SERONDOL | C10: 7041188000 | E10: DPT
A11: 32 | B11: PENGADAAN DAN PENGGANTIAN PROTEKSI BUSBAR DAN DIAMETER TERSEBAR DI WILAYAH UPT SEMARANG | C11: 5496945000 | D11: Masatek
A12: 34 | B12: PENINGKATAN KEANDALAN SALURAN TRANSMISI DI UIT JBB LINGKUP PENGGANTIAN KONDUKTOR DAN AKSESORIS DI UPT CILEGON | C12: 1163967360 | D12: Menunggu harga ACCC dari PLP, FU tgl 2 jan | F12: PT. Tuban Jaya Mandiri | H12: Pakai Ribe sesuai permintaan PLN | K12: Closing 19 Nov (minta isolator polymer, Huble) Tuban Menang, Nabil minta harga ke PLP untuk ACCC, kemarin nego harga
A13: 35 | B13: DPT MATERIAL ISOLATOR KERAMIK | D13: DPT | F13: PT. Kencana Alam Putra | K13: Closing 13 Des, klarifikasi sampul 1, gagal tidak ada sukses operasi 160kN dan sukses operasi dari UPT
A14: 39 | B14: PEKERJAAN MATERIAL UNTUK PEMERLIHARAAN DI WILAYAH UPT BOGOR | D14: HPS : 2.383.364.163 | F14: PT. INDODAYA NARATAMA ABADI | K14: Aanwijzing 19 des closing 8 January 25 Kalah sampul 1 PG Clamp tidak ada surat dukungan
A15: 42 | B15: PEKERJAAN PEMELIHARAAN PERALATAN ME DI GEDUNG THAMRIN KOPERBI JAKARTA | K15: gagal mengikuti karena tidak ada BPJS
A16: 7 | B16: PENGADAAN DAN PEMASANGAN REAKTOR 70 KV GARDU INDUK RUTENG SISTEM FLORES | C16: 216170300 | E16: 4 okt baru mulai sipilnya estimasi 3-4 bulan oct ini renc survey | F16: PT. Lembah Sentral Elektronindo | I16: Closing tgl 19 Desember, dalam masa sanggah, PLN terbitin surat pemenang | K16: status masih masih ada permntaan insulator Glass, PO akan diliris Feb-Maret, diinfokan ke kontraktor kemungkinan harga naik didatangin tgl 09 jan 25, tdk pakai PLP
A17: 30 | B17: PERKUATAN SISTEM PROTEKSI PETIR TERSEBAR DI WILAYAH UPT SEMARANG | C17: 8196840000 | D17: yg punya PWS, Pinjem bendera CKB pakainya Handal | E17: DPT
A18: 41 | B18: PENGADAN KABEL ON SHORE CONNECTION JETTY | C18: 8221900000 | F18: PT. INDODAYA NARATAMA ABADI | K18: kalah harga 1 : Jembo 6.577.520.000 2. 6.577.675.000 MKN 3 6.775.000.000 Voksel
A19: 43 | B19: PERABOT NON LOGAM ECATALOGUE 2024 | C19: 9936220500 | K19: yg lolos hanya Ruhui INA tdk lolos : 1 warna harusnya hitam hasil uji test tiap kursi
A20: 46 | B20: PEMBANGUNAN TRANSMISI 150 KV CIKUPA NEW – INC. (TERMASUK TOWER TX JATAKE – JATAKE II) | C20: 899987312 | F20: PT. KRAKATAU ENGINEERING & CONSTRUCTION | K20: Pemasukan 17 Januari Kalah sampul 1 update di eproc tidak masukan
A21: 48 | B21: PENGADAAN STRING SET EARTH WIRE AS 70 MM2 DAN JASA PENGGANTIAN STRING SET SERTA EARTH WIRE SUTT 150 KV KALIBAKAL-RAWALO-PLTU CILACAP T.01- 44 | C21: 742329430 | F21: PT MEGA ALFARIZKI | K21: Closing 23 Januari kalah yg menang Pelita Bumi Wangi pakai sicame
A22: 52 | B22: PEMBANGUNAN EXTENSION 2 LINE BAY GI 150 KV BALONGAN DAN PENYEMPURNAAN GI 150 KV BALONGAN | C22: 1568027310 | F22: KSO QDC – Buanareksa | K22: Closing 5 Feb, kalah harga pemenang Bisetta
A23: 24 | B23: Penambahan Grounding Langsung di UIT JBB Lingkup Penambahan Grounding di UPT Pulogadung pada SUTET 500 KV Tambun – Bekasi – Muara Tawar | C23: 188511200 | F23: PT. Tuban Jaya Mandiri | I23: Closing 4 Oktober | K23: Closing 4 Oktober, menunggu BA nego, sdh ttd kontrak 12 nov, mengajukan approval dwg ada beberapa pertanyaan ditgl 2 des, sdh dikirim pengajuan buat approval sdh survey kemungkinan pek. Awal tahun, ada perubahan design tidak pakai PLP
A24: 27 | B24: PEMBANGUNAN GI 150 KV JATILUHUR BARU | C24: 2347495545 | F24: PT. High Volt Technology | K24: Closing Jan, FU kalah pemenang WST
A25: 30 | B25: Penggantian Stringset dan Isolator Switchyard di GIS Salak Lama, GI Bogor Baru, dan GI Cileungsi | F25: PT. Tuban Jaya Mandiri | K25: Closing : 26 Feb, kalah harga pemenang Pandan Wangi
A26: 33 | B26: PEMBANGUNAN GARDU INDUK 150 KV KTT INDAH KIAT | C26: 1530336855 | F26: KONSORSIUM KAP – MJSU, PT. POWERCHINA INTELIGENSI DAN INTEGRITAS ENERGI TEKNOLOGI INDONESIA, PT. Niagamas Setiausaha | K26: Closing 22 Januari, kalah harga pemenang WST, KAP harga ke-2
A27: 34 | B27: Tender Ulang Pekerjaan Pembangunan Extension 1 Trafo Bay + Trafo 30 MVA Gardu Induk 150 kV Satui | C27: 224493100 | F27: PT. MEGA POWER TEKNINDO | K27: Closing 30 Januari 2025, Kalah harga pemenang Citra Bakti Persada
A28: 36 | B28: PENGADAAN STRING SET EARTH WIRE AS 70 MM2 DAN JASA PENGGANTIAN STRING SET SERTA EARTH WIRE SUTT 150 KV MRICA-WONOSOBO 1,2 T.1-108, SUTT 150 KV MRICA-PURBALINGGA 2 T.1-78 | C28: 1305633735 | F28: PT MEGA ALFARIZKI | K28: Closing 8 Feb, kalah harga pemenang pelita bumiwangi
A29: 37 | B29: PENGGANTIAN STRINGSET DAN ISOLATOR KOROSIF SUTT CIGERELENG – RAJAMANDALA – SUKALUYU – CIANJUR TAHAP 1 | C29: 282652500 | F29: PT. Kilat Wahana Jenggala | K29: Closing 20 Feb, kalah harga pemenang Global Twin Star
A30: 38 | B30: PEMASANGAN MULTI DIRECT GROUNDING (MDG) SUTT 70 DAN 150 KV TERSEBAR WILAYAH UPT BOGOR | C30: 2427276000 | F30: PT. Tuban Jaya Mandiri, PT Tesla Daya Elektrika | K30: Closing 24 Feb, TJM menang tidak pakai PLP pakainya KAK
A31: 39 | B31: PENGADAAN STRING SET EARTH WIRE AS 120MM2 DAN JASA PENGGANTIAN STRING SET SERTA EARTH WIRE SUTET 500 KV MANDIRANCAN – PEMALANG 1 T. 125-198 | C31: 462321680 | F31: PT MEGA ALFARIZKI | K31: Closing 25 Feb, kalah harga pemenang perintis sarana elektrik
A32: 42 | B32: PENGGANTIAN STRINGSET DAN ISOLATOR KOROSIF GI TERSEBAR DI WILAYAH UPT BANDUNG | F32: PT DUTA CAKRAWALA INDONESIA | K32: Closing 7 Maret, kalah harga pemenang GTS
A33: 30 | B33: PENGGANTIAN CT 500 KV P0 DI WILAYAH UPT BEKASI | C33: 147385728 | F33: PT DUTA CAKRAWALA INDONESIA | K33: Closing 10 Maret, Menang tdk pakai PLP
A34: 34 | B34: MODIFIKASI PENTANAHAN TOWER DI WILAYAH UPT PULOGADUNG TAHUN 2025 | K34: Closing 10 April, batak pemasukan, karna harga diatas pagu
A35: 3 | B35: PERKUATAN SISTEM PROTEKSI PETIR TERSEBAR DI WILAYAH UPT SEMARANG | C35: 8196840000 | K35: Tender terbatas, pemenang CKB
A36: 6 | B36: PEMBANGUNAN GI 150 KV JATILUHUR BARU | C36: 2347495545 | F36: PT. High Volt Technology
A37: 27 | B37: PENGGANTIAN KABEL POWER 20 KV TERSEBAR UPT BOGOR | F37: PT. Indevco Global | K37: Closing 26 Feb, Kalah harga
A38: 31 | B38: PEKERJAAN PENANGANAN TOWER KRITIS T.108 SIDRAP - MAKALE | C38: =533902300+282800 -> 534185100 | F38: PT Persada Indah Muda | H38: Closing 19 Maret | K38: Closing 19 Maret, Menang material pakai Hogn
A39: 33 | B39: PENGADAAN ALAT TERMOVISI | C39: 360000000 | F39: Indodaya Naratama Abadi | K39: Closing 15 April, tidak jadi pemasukan Permintaan OECD, Hrg Flir tidak masuk HPS
A40: 36 | B40: PENANGANAN ANOMALI TOWER KRITIS DI UPT MADIUN | C40: 1600000000 | K40: Closing 10 April, tidak lolos sampul 1 karna tidak ada pengalaman sejenis (Dinding Penahan Tanah)
A41: 9 | B41: Pengadaan Alat Uji Transmisi UPT Pontianak | K41: Tidak jadi
A42: 10 | B42: PENGADAAN POMPA BANJIR | K42: Tidak jadi
A43: 11 | B43: Pengadaan Perkuatan Pondasi dan Pengamanan Tower SUTT | K43: Tidak jadi
A44: 2 | B44: PENANGANAN ANOMALI TOWER KRITIS DI UPT MADIUN | C44: 1600000000 | F44: Indodaya Naratama Abadi | K44: Kalah gugur sampul 1 karna tdk ada pengalaman DPT yg menang bangun kreasi artha selisih 200jt
A45: 8 | B45: PENGADAAN ALAT KERJA PENDUKUNG K3 | F45: PT.Indodaya Naratama Abadi | K45: D&B 3A
A46: 21 | B46: PENGGANTIAN HV CLAMP DI UPT PROBOLINGGO | F46: PT CIPTA DAYA UTAMA | K46: Closing 19/05, tidak lolos tahap selanjutnya
A47: 2 | B47: PENGADAAN DAN PEMASANGAN ISOLATOR POLIMER GI PANAF, GI ROPA DAN GI ULUMBU DI PT PLN (PERSERO) UPT KUPANG | C47: 2383339800 | D47: Pagu : 2.456.200.000 | F47: Indodaya Naratama Abadi | K47: Kalah harga Pemenang Spektrum : 2.345.000.000 Harga INA : 2.383.339.800
A48: 8 | B48: PENGADAAN DAN PEMASANGAN ISOLATOR POLIMER GI PANAF, GI ROPA DAN GI ULUMBU DI PT PLN (PERSERO) UPT KUPANG | F48: PT. Kencana Alam Putra, KWJ, KMU | K48: Kalah harga Pemenang Spektrum : 2.345.000.000 Harga INA : 2.383.339.800
A49: 11 | B49: Feed for OPL Menggala North Waterflood Project'' | F49: KSO PT Patra Drilling Contractor & PT Enviromate Technology International | K49: Closing 24/05, tdk dikasih harga dari PLP
A50: 12 | B50: PENGADAAN ALAT TULIS KANTOR DI LINGKUNGAN PT KERETA COMMUTER INDONESIA TAHUN 2025 | C50: 1860002868 | F50: PT. Indodaya Naratama Abadi | K50: Kalah harga 1.617.907.696 11% dari hps
A51: 17 | B51: PERBAIKAN GROUNDING LANGSUNG DAN PEREMAJAAN GSW UNTUK PERBAIKAN SISTEM PENGAMANAN PETIR DI UPT MALANG | C51: 783511000 | F51: PT. Mega Alfarizki | K51: Closing 19 Mei, MA tdk masukin penawaran harga, dikarenakan hitungan diatas HPS
A52: 5 | B52: PEMBANGUNAN EXTENSION 6 LINE BAY GI TELUKJAMBE II (2 LINE BAY ARAH KTT AMAZON, 2 LINE BAY ARAH GI 150KV KTT INDAH KIAT, DAN 2 LINE BAY GI 150KV KARAWANG) | C52: 2060883500 | F52: PT. Wisma Sarana Teknik | K52: Menang harga dari handal 1M, harga modal dari PLP 1,461,579,130.00
A53: 11 | B53: PENYELESAIAN PENDING ITEM GI DAN TRANSMISI DALAM RANGKA STOP/STAP/STP PROYEK WILAYAH UPP JBT 1 | C53: 14886000 | F53: PT. Hydro Techno Utama | K53: Closing 25 Mei, Amsak Menang
A54: 12 | B54: PENYELESAIAN PENDING ITEM GI DAN TRANSMISI DALAM RANGKA STOP/STAP/STP PROYEK WILAYAH UPP JBT 2 | C54: 14886000 | F54: PT. Hydro Tec,hno Utama, PT. CITACONTRAC , PT Multi fabrindo | K54: Closing 25 Mei, Multi fabrindo menang pakai sicame
A55: 14 | B55: PEKERJAAN PENGADAAN DAN PENGGANTIAN SEALING END UPT PULOGADUNG | C55: 254500060 | F55: PT. High Volt Technology, PT. Indevco Global | K55: Closing 09/06, HVT tidak msaukan Indevco kalah
A56: 16 | B56: PENGADAAN DAN PENGGANTIAN SEALING END GIS 150 KV UPT CAWANG TAHAP 1 | F56: PT. Indevco Global | K56: Closing 09/06
A57: 27 | B57: PENGADAAN DAN PENGGANTIAN ISOLATOR BERIKUT STRINGSET SUTT 70KV KOSAMBI BARU-RENGASDENGKLOK #1 DAN #2 | C57: =D57*3% -> 178772223 | D57: 5959074100 | F57: PT. PSE | K57: sicame, selisih dengan PLP 20%
A58: 41 | B58: PENGGANTIAN TRAFO #3 GI 150 KV LOMANIS | C58: =D58*3% -> 1.0753691e+08 | D58: 3584563631 | F58: PT. Pelita Bumi Wangi | K58: masih minta harga stringset Purwokerto,
A59: 42 | B59: PENGADAAN STRING SET EARTH WIRE AS 70 MM2 DAN JASA PENGGANTIAN STRING SET SERTA EARTH WIRE SUTaT 150 KV KALIBAKAL-RAWALO-PLTU CILACAP T.01 - 44 | C59: =D59*3% -> 34227150 | D59: 1140905000 | F59: PT. Pelita Bumi Wangi | K59: masih minta harga stringset Purwokerto
A60: 30 | B60: PEKERJAAN PENGGANTIAN GSW MENJADI OPGW LINE BIMA-WOHA-DOMPU DAN EMPANG-PLAMPANG | C60: 952549600 | F60: PT. KELINCI MAS UNGGUL, PT. TESLA DAYA ELEKTRIKA | K60: Closing 26/05/2025, menunggu pengumuman pemenang, mbak laely FU ke KMU dan Tesla pakai merk apa, pemenang tender PT. Aneka Berkat
A61: 36 | B61: PENGGANTIAN GSW SUTT 150 KV MANDIRANCAN-NEW ARJAWINANGUN GT-T.1AB-T.29, MANDIRANCAN-SUNYARAGI T.30-T.39-GT,SUTT 70 KV JATIBARANG-ARJAWINANGUN GT-T.79-GT, DAN GSW SWITCHYARD GI 70 KV JATIBARANG | C61: 1189961080 | F61: PT TUNAS KARYA ADITAMA | K61: sdh menang dukungan awal IAG saat ini masih proses approval drawing FU Ikhbal Email ke pak Ari, SPH sudah dikirim Mbak laely FU 30/06, selisih 2,5% dari KPP
A62: 38 | B62: PENGADAAN DAN JASA PEMASANGAN STRINGSET DAN GSW AS 70 MM2 UNTUK MENGGANTI GSW KOROSIF PADA SUTT 150KV SEMENBARU-ITP T.1-T.29 | C62: =D62*3% -> 12350910 | D62: 411697000 | F62: PT ARCA ENERGI | K62: pinjem bendera
A63: 45 | B63: PENGADAAN DAN PENGGANTIAN TRAFO KONDISI BURUK WILAYAH TIMUR UITJBB LINGKUP JASA PENGGANTIAN TRAFO KONDISI BURUK DI GI CIKUPA | C63: 51883500 | F63: Duta Cakrawala indonesia, PT | K63: kalah harga
A64: 43 | B64: PEKERJAAN PENGGANTIAN MTU CT UNTUK AKTIVASI BUSPRO GI SINJAI | C64: 56313000 | F64: Kelinci Mas Unggul, PT | K64: Kalah harga PT. TALASALAPANG SULBAR
A65: 44 | B65: PEKERJAAN PENGGANTIAN MTU CT UNTUK AKTIVASI BUSPRO GI PANGKEP | C65: 56313000 | F65: Kelinci Mas Unggul, PT | K65: Kalah harga PT. TALASALAPANG SULBAR
A66: 45 | B66: Add HVC IBT 150 kV & GITET 500 kV Deltamas | C66: 35064000 | F66: PT. Sejahtera Mulia Kencana | K66: sdh PO menunggu DP approval drawing belum, PLNnya tidak jadi PO, minta surat pembatalan PO
A67: 50 | B67: PERBAIKAN GROUNDING LANGSUNG DI UPT MADIUN | F67: PT. Indodaya Naratama Abadi | K67: Tidak lolos S1, Data personalia tidak ada Tidak boleh KSO
A68: 58 | B68: PEKERJAAN JASA PEMASANGAN MTU CVT UPT PALU | F68: PT. KELINCI MAS UNGGUL | K68: Closing 31/07, tidak jadi pemasukan
A69: 54 | B69: PEKERJAAN REKONDUKTORING TRANSMISI 150 KV PARIT BARU – SIANTAN | F69: PT. KELINCI MAS UNGGUL | K69: Closing 31/07, tidak dikasih dukungan dan harga karna sudah di settle
A70: 59 | B70: Pengadaan Pekerjaan Pembangunan Extension Bay Coupler GI Sebangau | F70: PT. MEGA POWER TEKNINDO | K70: Closing 04/08, tidak jadi ikut pemasukan
A71: 26 | B71: PEMBANGUNAN EXTENSION 2 LINE BAY GI 150KV PINAYUNGAN (ARAH KTT MICROSOFT JKT02 & JKT09) | C71: 537119600 | F71: PT. MULTI FABRINDO GEMILANG | K71: Menang PLP,KAK, proses approval drawing mbak laely FU 13/06, material tidak pakai PLP pakai KAK, PLN UIP, penawaran PLP 339.800.000, menunggu update harga dari multifab, mau lewai di eproc kan
A72: 61 | B72: EXTENSION BAY TRAFO PAKET 2: EXTENSION TRAFO 3 GI 150 KV CIKARANG LIPPO DAN TRAFO 5 GI KV CIBATU | F72: PT. MEGA POWER TEKNINDO | K72: Closing 08/08, Dukungan melalui infotech
A73: 59 | B73: PENGGANTIAN ISOLATOR DI UPT BALI | C73: 7437497212 | D73: HPS 5,6 M | F73: PT. PERSADA INDAH MUDA, PT. Loka Sejahtera Abadi | K73: Closing 07/08
A74: 9 | B74: PENGGANTIAN TRAFO #1 150/20 KV 60 MVA GIS GROGOL DI UPT DURIKOSAMBI TAHUN 2024 DALAM RANGKA PENGADAAN DAN PENGGANTIAN TRAFO 150 KV KONDISI BURUK DI WILAYAH UITJBB LINGKUP PENGGANTIAN TRAFO WILAYAH UPT DURIKOSAMBI | C74: 1282500 | D74: Dalian | F74: PT. Indevco Global | K74: Closing 27 Mei, Menang, SPK sdh diterima nunggu info trafo (rencana pakai merk unindo) dari dari PLN, rencana minggu ini ke Indevco, trafo belum ready
A75: 48 | B75: PENGADAAN DAN PENGGANTIAN ISOLATOR KONDISI KRITIS TERSEBAR DI WILAYAH UNIT INDUK TRANSMISI JAWA BAGIAN TIMUR DAN BALI (PENGADAAN ISOLATOR KERAMIK | C75: 10803335970 | F75: PT KARYASEMBADA CIPTAMANDIRI | K75: Closing 23/07, kalah gugur sampul 1 karna surat dukungan keagenan (STP), Lolos KAP, Mulya Jatra, Mitra persada
A76: 44 | B76: GI 150 KV KRUENG RAYA EXT TRAFO (1x60) MVA | C76: 233470076 | F76: Dungo Reksa, NPC | K76: mundur Closing 15 Agustus, NPC Gagal sampul 1 adminitrasi
A77: 45 | B77: GI 150 KV TAKENGON EXT TRAFO (1x60) MVA | C77: =195102800+160041200 -> 355144000 | F77: NPC | K77: Closing 25 Juli, PLP janji hari ini kirim SPH, NPC Gagal sampul 1 adminitrasi
A78: 50 | B78: PEMASANGAN KABEL POWER TERSEBAR DI UPT MADIUN | C78: 4569600 | F78: PT KARYASEMBADA CIPTAMANDIRI | K78: Closing 05/08, masih evaluasi sampul 1, tidak lolos sampul 1 tidak dapat dukungan 3d scanner
A79: 37 | B79: UPRATING GI 150 KV SANGGRAHAN BAY MEDARI, BAY KENTUNGAN ; GI 150 KV MEDARI BAY SANGGRAHAN | C79: =668364920+1350888251 -> 2019253171 | F79: PT KENCANA ALAM PUTRA | K79: Menang tidk pakai PLP, pakai KAK selisih 25% insulator pakai suzho
A80: 52 | B80: PEKERJAAN EXTENSION BAY TRAFO PAKET 3 DI GI 150 kV JEPARA DAN GI 150 kV JEKULO | C80: 260531600 | F80: PT. Global Twin Star, PT. MPT | K80: Closing 08/08, tidak pakai PLP, pakai handal selisih 20%
A81: 53 | B81: PENGADAAN STRINGSET ISOLATOR DAN JASA PENGGANTIAN STRINGSET SERTA ISOLATOR 120 KN UNTUK SUTT 150 KV PEMALANG - TARUB 1,2 T.1-59A DAN SUTT 150 KV TARUB - KEBASEN 1,2 60A-78 | C81: 1655790500 | F81: PT. Duta Cakrawala Indonesia, PT PERSADA INDAH MUDA | K81: Kalah PIM selisih 300 jt sama PSE DCI turun 7% PSE 12%
A82: 57 | B82: PENGADAAN BARANG DAN JASA KONSTRUKSI GI 150 KV BUNGAH / JIIPE EXTENSION TRAFO BAY | C82: 101208000 | F82: PT. MEGA POWER TEKNINDO, PT. Binabuana Sewaka | K82: Closing 30/07, harga PLP lebih mahal 50% dari handal, pemenang Purnama Indonesia
A83: 58 | B83: PENGGANTIAN TRAFO #1 GI 150 KV DIENG | C83: 8910000 | F83: PT. Duta Cakrawala Indonesia, | K83: Closing 06/08, kalah, pemenang smthree
A84: 77 | B84: insulator stock GIG 120kN Antifog | C84: =500*317000 -> 158500000 | F84: Persada Engineering & Contruction - Kamesa | K84: Melalui KPP
A85: 16 | B85: PEMBANGUNAN GIS 150 KV GANDUL II/PAMULANG BESERTA SUTT 150 KV GANDUL II/PAMULANG – INC (SERPONG – BINTARO) | C85: =663541600+856087624 -> 1519629224 | F85: KSO PT. HASTA PRAJATAMA – PT. HIGH VOLT TECHNOLOGY, CITICON CONSORTIUM, NPC | K85: TL pakai PLP GI pakai Handal, mundur 20 Agustus, FU ketemuan kamis atau jumat tgl 31 dengan citicon mbak laely, masih evaluasi di tim manajemen, Kalah, Pemenang IMURA (182M), no 2 NPC (195M) no 3 Citicon (198M) Indokomas (203M) citramas (205M) Hasta Praja (207M) Twing (218M)
A86: 20 | B86: TLA DI WILAYAH PENGADAAN DAN PEMASANGAN UNIT INDUK TRANSMISI JAWA BAGIAN TENGAH | C86: 399968000 | F86: PT. Bisetta | K86: tender ulang pemasukan 17 July, mbak laely FU ke pak Tholib enindo, fu Tgl 04/08 masih evaluasi, belum ada update dari PLP, KALAH
A87: ='Done 2019 - 2025'!#REF!+1 -> #REF! | B87: PEKERJAAN PENGGANTIAN AIR BUSHING GISTET KEMBANGAN DAN CAWANG BARU | C87: 11949000 | F87: PT. ENINDO ORBITAMA, PT. DELTA SINAR PERKASA | K87: kalah
A88: ='Prospek 2025'!#REF!+1 -> #REF! | B88: PENGGANTIAN AIR BUSHING DI WILAYAH UITJBB | C88: 11949000 | F88: PT ENINDO ORBITAMA, PT DELTA SINAR PERKASA | K88: kalah harga diatas hps
A89: =Loss!A96+1 -> 31 | B89: PEKERJAAN PEMBANGUNAN GI 66 KV ALAS EXT 30 MVA | C89: 148560000 | F89: PT. CITRA BAKTI PERSADA, PT. NIAGAMAS SETIAUSAHA | K89: kalah pemenang indokomas Indokomas 28.448.190.00 Niagamas Setiausaha 29.861.228.341 Citra Bakti Persada 30.990.885.771 Iradat Aman Globalindo 31.938.000.000 QDC Technologies 33.589.836.770
A90: =Loss!A88+1 -> 31 | B90: Pekerjaan Pengadaan dan Pemasangan Extension Bay Trafo 4 GI 150 kV Bantul | C90: 260574700 | F90: PT. MEGA POWER TEKNINDO | K90: Closing 11/08, masih evaluasi, harga diatas HPS
A91: =A90+1 -> 32 | B91: Pekerjaan Pengadaan dan Pemasangan Extension Bay Trafo 3 di GI 150KV Margakarya | C91: 212565400 | F91: PT. MEGA POWER TEKNINDO | K91: Closing 18/08, masih evaluasi harga diatas HPS
A92: =Loss!A94+1 -> 39 | B92: PENGADAAN DAN PEMASANGAN KUBIKEL DI UPT MALANG | C92: 9139200 | F92: PT KARYASEMBADA CIPTAMANDIRI | K92: Closing 13/08, kalah sampul 1 tidak dapat dukungan 3d laser
A93: ='Prospek 2025'!#REF!+1 -> #REF! | B93: BFLL ORB | F93: Hexa | K93: menunggu info PLP US, udh ngasih harga
A94: ='Prospek 2025'!#REF!+1 -> #REF! | B94: PEMBANGUNAN GI 150 KV SELARU DAN SUTT INC. 2 PHI (BATULICIN – KOTABARU) - SELARU | C94: 2096047586 | E94: BAP Indokomas, Dalima, QDC, HKP | F94: KSO HKP – INDISI | K94: pemenang hasta praja selisih 11,32%
A95: ='Prospek 2025'!#REF!+1 -> #REF! | B95: PENGGANTIAN ISOLATOR KERAMIK DI UPT SURABAYA | C95: 3508295916 | F95: PT. Persada Indah Muda | K95: Closing 26/08, Evaluasi sampul 1, kalah pakai ribe
A96: ='Prospek 2025'!#REF!+1 -> #REF! | B96: PENGGANTIAN ISOLATOR DI UPT MALANG | C96: 3127927504 | F96: PT MEGA ALFARIZKI | K96: Closing 15/08, pakai PLP LULUS sampul 1, kalah, pemenang Cahaya Karya Bersama
A97: 40 | B97: EXTENSION TRAFO BAY 60 MVA GI 150 KV CENDANA | C97: 283943700 | F97: PT. CITRA BAKTI PERSADA, PT. Mega Power Teknindo, HKP | K97: kalah, pemenang multifab pakai handal
A98: 41 | B98: EPC Poigar-2 HEPP Contactor BIDDING (2x15MW) / Pelelengan Kontraktor EPC PLTA Poigar-2 (2x15MW) | C98: =1480740800+1398240000 -> 2878980800 | F98: PT NPC | K98: sdh dikirim ke NPC dukungan dan harga, closing 19/09, SBU konsorsium kunmi belum jadi sampai closing tender
A99: 57 | B99: PENGGANTIAN ISOLATOR POST PADA TIANG BETON TIPE I DI UPT BALI | C99: 1275496700 | F99: PT MEGA ALFARIZaKI | K99: Menang material pakai sicame TPG PLP tidak masuk
A100: 58 | B100: PEKERJAAN PENGADAAN DAN PEMASANGAN EXTENSION BAY TRAFO-3 DI GI 150 KV TAMAN MEKAR | C100: 318.073.400 | F100: PT. Lembah Sentral Elektronindo | K100: Kalah, pemenang permata jaya teknik
...

Sheet Done 2019 - 2025
A1: Project Done
A3: No | B3: Project Name | C3: Value | D3: Nama Kontraktor | E3: Desc | F3: PLP Promise | G3: Remark Kontraktor | H3: Remak PLP | I3: Remarks | J3: PIC
A4: 1 | B4: GI 150 kV SINTANG | D4: Buanareksa | E4: STRINGSET DAN HV CONNECTOR | F4: 43490 | G4: PICK UP 25 JANUARI 2019, WAITING FOR PACKING LIST FROM PLP | I4: DONE | J4: Priyo
A5: 2 | B5: GI 150 kV KENDAWANGAN | D5: Buanareksa | E5: STRINGSET DAN HV CONNECTOR | F5: 43490 | G5: PICK UP 25 JANUARI 2019, WAITING FOR PACKING LIST FROM PLP | I5: DONE | J5: Priyo
A6: 3 | B6: GI 150 kV APP PULOGADUNG | D6: KPG | E6: HV CONNECTOR | F6: 43490 | G6: PICK UP 25 JANUARI 2019, WAITING FOR PACKING LIST FROM PLP | I6: DONE | J6: Priyo
A7: 4 | B7: GI 150 kV MATARAM | D7: Purnama | E7: STRING SET DAN HV CONNECTOR PROSES PRODUKSI | F7: 43528 | G7: CONTRACTOR REQUEST STRINGSET END OF JANUARY | I7: DONE | J7: Priyo
A8: 5 | B8: 150KV GI CAWANG EXT | D8: Amanda | E8: STRINGSET DAN HV CONNECTOR, PROSES ANTRIAN | F8: 43529 | G8: CONTRACTOR REQUEST STRINGSET MID FEBRUARY | I8: DONE | J8: Brian
A9: 6 | B9: 150KV GIS NUSA DUA HVC | D9: Sastra Mas | E9: HV CONNECTOR | F9: 43488 | G9: DONE | I9: DONE | J9: Aco & Brian
A10: 7 | B10: 275 kV TL SIGLI - ULEE KARENG (SECTION 1,2 DAN 3) | D10: BBC | E10: STRING SET DAN ACCESSORIES | F10: 43532 | G10: SECTION 1 (MINUS ARCH.HORN), SECTION 2 AND 3 NEED REPORT PROGRESS , TIME LEFT ONLY 1 MONTH | I10: DONE | J10: Aco & Brian
A11: 8 | B11: 150KV GIS GUNUNG SARI | D11: Sastra Mas | E11: STRINGSET DAN HV CONNECTOR | F11: 43539 | G11: CONTRACTOR REQUEST MID FEBRUARI | I11: DONE | J11: Priyo
A12: 9 | B12: PROYEK TOL JAPEK 2 PHASE 2 | D12: DCM | E12: PROSES PRODUKSI | F12: 43507 | G12: NEED ADVISE FROM PLP ABOUT PO REVISION, TIME LEFT ONLY 2 WEEKS | I12: DONE | J12: Eko
A13: 10 | B13: 150 KV TL JABABEKA BABELAN | D13: CMS | E13: STRINGSET DAN HV CONNECTOR, SUDAH PACKING | F13: 43504 | G13: WAITING SPACER 17 PCS | I13: DONE | J13: Eko
A14: 11 | B14: 150KV GI TJBT KAPASITOR 7 SITE | D14: TDKK | E14: STRINGSET, PROSES PACKING MINGGU INI | F14: 43493 | G14: NEED REPORT PACKING STATUS | I14: DONE | J14: Fuad
A15: 12 | B15: 150KV GI PAMEKASAN STRING | D15: PPWS | E15: STRINGSET | F15: 43504 | G15: NEED REPORT FROM PLP MATERIAL STATUS | I15: DONE | J15: Eko
A16: 13 | B16: TL 150 kV Caruban Tower 51 - 52 (SOKER) | D16: Matrix | E16: STRINGSET & Isulator | F16: End of Juni 2019 | G16: Approval Drawing | I16: DONE | J16: Eko
A17: 14 | B17: TL 150 kV Nganjuk - Caruban Tower 24 - 25 (SOKER) | D17: Matrix | E17: STRINGSET & Isulator | F17: End of Mei 2019 | G17: Approval Drawing | I17: DONE | J17: Eko
A18: 15 | B18: TL 500 kV Paket 1 dan 2 Additional | D18: Waskita Karya | E18: STRINGSET | F18: End of 12 April 2019 | G18: Approval Drawing | I18: DONE | J18: Brian
A19: 16 | B19: TL 150 kV KM 27 Cikarang Listrindo | D19: DCM | E19: STRINGSET | F19: End of Mei 2019 | G19: Sudah PO | I19: DONE | J19: Eko
A20: 17 | B20: GI 150 kV Sopeng | D20: Dipajaya | E20: Post Insulator | F20: End Of 07 Juli 19 | G20: - | I20: DONE | J20: Laely
A21: 18 | B21: TL 150 kV Krian - Manyar (KLBM) | D21: Matrix | E21: STRINGSET & Isulator | F21: End of Mei 2019 | G21: Belum terima Revisi PO dari kontraktor | H21: Siap di week 3 | I21: DONE | J21: Komunikasi dengan bu Zaki terkait komitment (Brian)
A22: 19 | B22: CISUMDAWU PHASE 3 (Tower Permanent) | D22: Kedung Jaya | E22: STRINGSET | F22: 43686 | G22: Sudah Lunas | I22: DONE | J22: Priyo
A23: 20 | B23: TL 150 kV CK 26 Cikarang Listrindo | D23: ALHAS | E23: STRINGSET | G23: DONE | I23: DONE | J23: Aco
A24: 21 | B24: Add Komponen Hawk | D24: Pelita Bumi Wangi | E24: Komponen HWK | G24: DONE | I24: DONE | J24: Brian
A25: 22 | B25: GI 150 KV UNGARAN | D25: Celindo | E25: STRINGSET DAN HV CONNECTOR | F25: End of Maret 2019 | G25: DONE | I25: DONE | J25: Priyo
A26: 23 | B26: GI 150 kV PADANG SAMBIAN | D26: Sastra Mas | E26: STRINGSET DAN HV CONNECTOR, PROSES ANTRIAN | F26: 43579 | G26: DONE | I26: DONE | J26: Fuad
A27: 24 | B27: GIS 150 kV Jatake | D27: Lumintu | E27: STRINGSET DAN HV CONNECTOR | G27: SKBDN sudah cair tgl 6 Desember 2019 (DONE) | I27: DONE | J27: Priyo
A28: 25 | B28: TL 150 kV Rengat Tembilahan | D28: Waskita Karya | F28: End of Agustus 2019 | G28: pembayaran 31 Desember 2019 DONe | I28: DONE | J28: Ibu Sari
A29: 26 | B29: GI 150 KV Balong Bendo | D29: GTS | E29: STRINGSET DAN HV CONNECTOR | F29: 15 Okt 2019 | G29: Sudah PO, Giro sudah di bayar 27 Desember 2019 | I29: DONE | J29: Fuad & Brian
A30: 27 | B30: GITET 500 kV Kediri | D30: Mahakaam | E30: STRINGSET DAN HV CONNECTOR | F30: AO 11 Okt 2019 | G30: Sudah PO, crosscheck pengambilan dari Pa Aksa ke Brian untuk PI dan Dics Insulator sudah di ambil giro nya sudah di serahkan di FU lgi mas brian | I30: DONE | J30: Priyo
A31: 28 | B31: Gi Balaraja | D31: Mahakam | E31: PI dan Connector | G31: kontraktor sudah PO ke Alam | I31: DONE | J31: Fuad
A32: 29 | B32: GI 150 kV Semen Grobogan | D32: KAP | E32: STRINGSET DAN HV CONNECTOR | F32: End of Agustus 2019 | G32: kontrkator sudah PO stringset dan connector, kontraktor sudah ambil parsial stringset disc insulator dan PI kontraktor ambil parsial stringset cek sama PLP sore ini 6 Februari 2020 - pembayaran DP Sudah | H32: Minta PL Sore ini tgl 13 atau 14 februari 2020 akan diambil string nya dulu | I32: DONE | J32: Priyo
A33: 30 | B33: GI 150 kV Tolitoli | D33: Fuji SME | E33: STRINGSET DAN HV CONNECTOR | F33: End of Juli - Agustus 2019 | G33: Toli toli Sudah d bayar | H33: Di ambil hari ini tgl 24 Februari 2020 | I33: DONE | J33: Fuad
A34: 31 | B34: GI 150 kV Bangkir | D34: NSU | E34: STRINGSET DAN HV CONNECTOR | G34: pembayaran giro akhir januari 2020 sudah bayar | H34: - | I34: DONE | J34: Fuad
A35: 32 | B35: GI Suralaya, Cilegon Lama, PETDO | D35: KSCM | E35: Connector | G35: sudah ada drawing nya | I35: DONE | J35: Brian
A36: 33 | B36: TL 150 kV Ulee Kareng Krueng Raya Add1 | D36: BBC | G36: PO Kontraktor Minggu ini tgl 20 Januari 2020 sudah dibayar tgl 20 Februari 2020 | I36: DONE | J36: Fuad
A37: 34 | B37: GI Cawang | D37: PT Elektrika | E37: Connector | F37: Januari 2020 | I37: DONE | J37: Priyo
A38: 35 | B38: GI 150 kV Labuhan | D38: Sastramas | E38: STRINGSET DAN HV CONNECTOR | G38: sudah dibayar tgl 3 Maret 2020 | H38: 2 item Connector sudah selesai | I38: DONE | J38: Fuad
A39: 36 | B39: GI 150 kV BABAKAN BARU, Indramayu | D39: TDKK | E39: STRINGSET DAN HV CONNECTOR | G39: sudah di kirim ke site, pembayaran giro udah cair | I39: DONE | J39: Priyo
A40: 37 | B40: TL 150 kV NEW BALIKPAPAN | D40: Waskita Karya | E40: STRINGSET | F40: 19 Maret 2020 | I40: DONE | J40: Priyo
A41: 38 | B41: Relokasi Jababeka Babelan | D41: Alhas | E41: Dead End | H41: PLP Sudah kirim AO | I41: DONE | J41: Aco
A42: 39 | B42: GIS 150 kV Ulin | D42: Distraco | E42: STRINGSET DAN HV CONNECTOR | G42: sudah PO | I42: DONE | J42: Priyo
A43: 40 | B43: GI Cikarang | D43: KPG | E43: Stringset dan connector | I43: DONE | J43: Priyo
A44: 41 | B44: Material Cadang | E44: CCDE | I44: DONE
A45: 42 | B45: UPT Manado | E45: Aksesoris Tower | G45: Sudah Bayar | I45: DONE | J45: Aco
A46: 43 | B46: Penggantian Insulator beserta Stringset Suspension | D46: Stringset dan Insulator | E46: 83000000 | F46: UPT Salatiga (PT. Quinad Bahana Indonesia) | H46: Kontraktor sudah PO | I46: DONE | J46: Priyo
A47: 44 | B47: GI 150 KV KEBUMEN | D47: BBS&Libratama | E47: STRINGSET, DISC INSULATOR, & PI | G47: PL string set sudah ada, PL connector sudah | I47: DONE | J47: Priyo
A48: 45 | B48: TL 150 kV - KCIC DK 125 (Kereta Api Cepat) | D48: CMS | E48: STRINGSET | G48: sisanya pembayaran kurang 900 juta dan PO kurang dari 1000 insulator minggu ini diterima, barang blm di ambil masih menunggu keputusan gudang nya mereka | H48: material sudah siap di marunda sudah dambil | I48: DONE | J48: Priyo
A49: 46 | B49: ACSR Zebra Dead and Saglink | D49: PLN UPT Salatiga | I49: DONE | J49: Priyo
A50: 47 | B50: Penggantian Kawat Petir AS 120mm | D50: PLN UPT Salatiga | H50: Sudah PO menunggu material dari PLP selesai akhir september | I50: DONE | J50: Priyo
A51: 48 | B51: GI 150 kV Tolinggula | D51: NSU | E51: STRINGSET DAN HV CONNECTOR | G51: PO Pertama barang sudah diambil belum bayar, PO kedua Add masih di gudang belum di bayar, sudah bayar sebagian | H51: - | I51: DONE | J51: Fuad
A52: 49 | B52: Rekonduktoring GSW 55 (UPT Gresik) | D52: KAP | E52: +/- 340 Tower | I52: DONE | J52: Priyo
A53: 50 | B53: GI Bandara & GI Palangkaraya | D53: Distraco | H53: Due Date PO 16/2/2021 | I53: DONE | J53: Priyo
A54: 51 | B54: TL Ulee Kareng | D54: BBC | E54: Stringset | I54: DONE | J54: Priyo
A55: 52 | B55: TL & GI Banda Aceh | D55: Saptaguna | E55: Stringset & Connector | I55: DONE | J55: Priyo
A56: 53 | B56: Pengadaan Accesories AS UPT Purwokerto | D56: PT. Mega Alfarizki | I56: Done | J56: Fuad
A57: 54 | B57: GI Mintin | D57: MPT | E57: Connector | J57: Priyo
A58: 16 | B58: Pemasangan Proteksi Independent Ground Wire Transmisi 150kV | D58: SSA (Sarindo Sukses Asia) | E58: Komponen Stringset & Insulator | I58: PO Insulator sudah (Lunas) | J58: Priyo
A59: 8 | B59: Stringset dan Jasa Penggantian GSW Switchyard pada GI Cibinong - UPT Bogor | C59: 155474220 | D59: KSO Panda Wangi - MCPU | E59: Sudah PO | G59: Stringset
A60: 9 | B60: UPT Purwokerto (Kesugihan - Lomanis) | C60: 269660200 | D60: KSCM | E60: Sudah PO | H60: 26 Juni 2021 | I60: DONE
A61: 10 | B61: UPT Purwokerto (Purworejo - Kebumen) | C61: 346900800 | D61: KSCM | E61: Sudah PO | H61: 26 Juni 2021 | I61: DONE
A62: 11 | B62: UPT Purwokerto (Balapulang - Bumiayu) | C62: 146880900 | D62: KSCM | E62: Sudah PO | H62: 26 Juni 2021 | I62: DONE
A63: 13 | B63: KHS - Pengadaan dan Pemasangan Stringset di UPT Salatiga | C63: 75745000 | D63: CDU | E63: Sudah PO | G63: Baut dengan 3 ukuran masing2 76 pcs dikembalikan ke PLP | I63: DONE
A64: 14 | B64: Pengadaan String Set Earth Wire dan Jasa Penggantian string set beserta GSW yang Korosif | C64: 255489000 | D64: Mega Alfarizki | E64: Sudah PO | G64: Stringset | I64: DONE
A65: 15 | B65: GI Cilegon | C65: =43398700+5429250 -> 48827950 | D65: GTS | E65: Sudah PO | G65: HVC dan Stringset | H65: 11 Juni 2021 | I65: DONE
A66: 16 | B66: Penggantian IBT GI Wayang Windu dan Cigelereng | C66: 134000000 | D66: NSU | E66: String Set Connector | G66: PO additional belum selesai | H66: menunggu AO dari PLP | I66: DONE | J66: Fuad
A67: 17 | B67: GI Stara | C67: 10170600 | D67: PT. Cahaya Karya Sentosa | E67: Material Komponen | F67: 2 Juli 2021 | G67: sudah lunas | I67: DONE
A68: 18 | B68: GI Stara Add | C68: 2933000 | D68: PT. Cahaya Karya Sentosa | E68: Material Komponen | F68: SOH | G68: sudah PO ke ALAM | I68: DONE | J68: Fuad
A69: 14 | B69: Baut GISTET Adipala | C69: 31897200 | D69: CDU | E69: Baut | I69: DONE | J69: Fuad
A70: 7 | B70: GI 150 kV PLTU Gresik (Ext) | C70: 105863300 | D70: Mahakam | F70: - HVC : 10 Juni 2021 - Stringset : 28 Juli 2021 | G70: menunggu PO add | I70: barang sudah diambil, cover giro 31/12/2021 | J70: Fuad
A71: 9 | B71: Penggantian Kawat Petir Pedan - Klaten | D71: Mega Alfarizki | E71: Komponen Stringset | G71: Operasional Masih OFF | I71: FU lagi ke kontraktor | J71: Fuad
A72: 10 | B72: Pengadaan Armor Rods | C72: 62580000 | D72: PT. Wikon | E72: Armor Rod | G72: Masih Proses Penagihan | H72: Material dikirim tgl 16 Maret 2021 | I72: menunggu pembayaran | J72: Fuad
A73: 11 | B73: GI Semen Grobogan Add | C73: 60770400 | D73: PT. Kencana Alam Putra | E73: HVC dan Stringset | G73: menunggu giro dari kontraktor, material sudah dikirimkan | I73: barang sudah diambil, cover giro 11/9/2021
A74: 12 | B74: Pengadaan Material Shackle dan Turnbuckle 120 kN | C74: 136590000 | D74: PT PLN UPT PURWOKERTO | E74: Material Komponen | F74: - Turnbuckle: Akhir September | I74: material selesai 15 September, denda 1% per hari keterlambatan, rencana kirim paling lambat 15-16 September, kontrak habis 22 Agustus 2021 | J74: Fuad
A75: 13 | B75: Baut UPT Salatiga | C75: 75745000 | D75: CDU | E75: Baut | I75: pengiriman selesai, pembayaran akhir bulan (Agustus 2021) | J75: Brian
A76: 15 | B76: SPACER JOINT Pemalang - Ungaran Mandirancan | C76: 130715000 | D76: CDU | E76: spacer joint | F76: 20 Agustus 2021 | I76: sudah DP, menunggu info material selesai dari PLP (harusnya 20 Agustus 2021), Keu siapkan Proforma Invoice | J76: Fuad
A77: 16 | B77: GI SURABAYA BARAT | C77: 253460600 | D77: Binabuana Sewaka | F77: 44456 | G77: sudah DP 2 Agustus 2012 | I77: menunggu material selesai | J77: Fuad
A78: 17 | B78: PSPP PAPUA | C78: 69507000 | D78: Mitratek Bangun Gemilang | F78: 44446 | G78: meminta percepatan 31 Agustus 2021 | I78: material selesai 7 September 2021 | J78: Fuad
A79: 18 | B79: Accessories AS UPT Salatiga | C79: 101932854 | D79: GTS | F79: Partial Shipment | G79: sudah DP, bayar yang sudah siap | I79: material sudah siap, menunggu pembayaran dari GTS (pembayaran ke-3; 56.795.654) | J79: Fuad
A80: 19 | B80: Pengadaan Shackle 210 kN | C80: 57475000 | D80: PT PLN UPT PURWOKERTO | G80: sudah mengeluarkan SPK (due date 16-Okt-2021) | I80: menunggu best price PLP | J80: Fuad
A81: 4 | B81: PEMBANGUNAN BAY KAPASITOR 25 MVAR GARDU INDUK 150 KV BATULICIN | C81: 77233400 | D81: PT Lembah Sentral Elektrindo | E81: STRINGSET DAN HV CONNECTOR | G81: sudah PO, Stringset belum di ambil | H81: Menunggu Pengambilan Stringset | I81: pembayaran sudah lunas
A82: 5 | B82: PENGANTIAN KAWAT GSW DALAM RANGKA PENGGANTIAN DAN PENYEMPURNAAN PERALATAN INSTALASI DI UPT PULOGADUNG | C82: 214693600 | D82: KSO KARYA PUTRA GEMILANG & PT MEDIAN ELEKTRA PERKASA | E82: STRINGSET | F82: Awal Maret | G82: Lunas 100% | I82: material dari Sicame selesai di 31 Maret 2022, Invoice minta di siapakan ke Bagian Keuangan, minta Packing List
A83: 10 | B83: PEMINDAHAN PANEL KONTROL DAN PROTEKSI DI GARDU INDUK GUDANG GARAM | C83: 29743776 | D83: PT Global Twin Star | E83: STRINGSET + Insulator | F83: 18 Maret 2022 | G83: info diambil awal bulan April | I83: menunggu pengambilan material oleh kontraktor di PLP dan Insulator di Gudang UGC
A84: 11 | B84: PENGADAAN SHACKLE 120 KN DAN BALL EYE 120 KN UNTUK PENGGANTIAN AKSESORIF KOROSIF Nomor : 007.SPKPB/DAN.01.01/C35050000/2022 | C84: 264108000 | D84: PLN UPT PURWOKERTO | E84: HVC | F84: 44606 | I84: minta TPG & TKDN ke PLP, minta pengambilan material di tgl 18 April 2022 Approval TPG Belum diberikan PLN
A85: 12 | B85: PENGADAAN TURN BUCKLE 120 KN, SUSPENSION CLAMP GSW, STRAIN CLAMP GSW UNTUK PENGGANTIAN AKSESORIS KOROSIF 008.SPKPB/DAN.01.01/C35050000/2022 | C85: 214890000 | D85: Done, menunggu Payment | E85: PLN UPT PURWOKERTO | F85: HVC | G85: 44665 | H85: minta dokumen legal AI dan pembanding INA | I85: estimasi pengiriman tanggal 18 April 2022
A86: 5 | B86: PENGGANTIAN KAWAT GSW BESERTA STRINGSET SUTT 150 KV WILAYAH UPT DURIKOSAMBI TAHUN 2021 PENANGANAN TOWER KRITIS DAN PENGAMANAN ASET SALURAN TRANSMISI DI WILAYAH UPT DURIKOSAMBI PAKET 1 | C86: 256717000 | D86: Sudah PO, sudah bayar sebagian (material parsial) | E86: PT DUTA CAKRAWALA INDONESIA | F86: STRINGSET | H86: material sudah di pick up parsial (22 April 2022), sisa 1 item | J86: Warning Ball tiba Mei 18 2022, sesuai PL ke PLP | N86: menunggu info dari PLP
A87: 3 | B87: PENGADAAN DAN PEMASANGAN BAY REAKTOR 30 MVAR GARDU INDUK 150 KV KUARO | C87: 251278500 | D87: Sudah PO | E87: PT Lembah Sentral Elektrindo | F87: STRINGSET DAN HV CONNECTOR | H87: menunggu konfirmasi kapan di pick up | I87: konfirmasi update status GIG | J87: Dibuatkan packing list Insulator apakah pake GIG/ABI | M87: Gelwin | N87: sudah lunas
A88: 10 | B88: PENGADAAN U-BOLT GSW 120 KN , SOCKET CLEVIS 120 KN, EYE LINK 120 KN, TONGUE SOCKET 120 KN UNTUK PENGGANTIAN AKSESORIS KOROSIF 006.SPKPB/DAN.01.01/C35050000/2022 | C88: 255460000 | D88: SPK | E88: PLN UPT PURWOKERTO | F88: HVC | G88: 44606 | H88: socket tongue masih belum diterima terkait perkapuran, menunggu report tertulis dari bagian Mutu PLN (jumlah reject dan diterima) | I88: material socket tongue produksi baru selesai +/- 11 - 18 Mei 2022 (import) | J88: denda keterlambatan 10.000.000 | N88: menunggu pembayaran dari PLN
A89: 11 | B89: Rekonduktoring Busbar sisi Bay 150 kV IBT 4 dari 1xTAL 850 menjadi 2xTAL 850 | C89: 48819876 | D89: PO | E89: PT. MAHAKAAM JAYA SEJAHTERA | F89: STRINGSET | G89: 44722 | H89: menunggu pembayaran pick up hari jumat 17 Juni 2022
A90: 16 | B90: Perbaikan Konduktor Rantas - ACSR 240mm2 | C90: 14190300 | D90: LUNAS | E90: CAHAYA KARYA BERSAMA, PT | F90: ACCESSORIES | J90: tinggal kirim | M90: Gelwin
A91: 18 | B91: Penggantian Kabel Power di Wilayah UPT Durikosambi Tahun 2022 | C91: 15388800 | D91: Sudah PO | E91: DUTA CAKRAWALA INDONESIA, PT | F91: Post insulator 33kv+triangle
A92: 9 | B92: PENGADAAN DAN PEMASANGAN RELAY BUSBAR PROTECTION DI 5 GI | C92: 273893760 | D92: Sudah PO | E92: PT Global Twin Star | F92: HVC | H92: menunggu PO kontraktor | J92: Beli baut 3000 pcs (Galvanized)
A93: 12 | B93: Renewal Corona Ring 275kV | C93: 164065000 | D93: PO kontraktor | E93: PT MULTI PRATAMAINDO | F93: FITTING | H93: estimasi material sampai site hari Rabu/Kamis (31/1) | I93: on progress | J93: menunggu pengiriman menuju Site, minta Dokumentasi ke forwarder | L93: Pembayaran sudah selesai | N93: MacLean
A94: 6 | B94: REKONFIGURASI GI 150 KV NAGAN RAYA | C94: 1000249410 | D94: Sudah PO | E94: PT SAPTAGUNA UTAMA | F94: STRINGSET, FITTING & INSULATOR | I94: Stringset 26 Agustus 2022 Insulator 16 September 2022 | J94: Siapkan baut dan post insulator dan disk insulator dan packing list
A95: 7 | B95: PENGGANTIAN MTU CB DALAM RANGKA PENGGANTIAN DAN PENYEMPURNAAN PERALATAN INSTALASI DI WILAYAH UIT JBB - UPT DURIKOSAMBI TAHUN 2022 | C95: 11955000 | D95: Sudah PO | E95: DUTA CAKRAWALA INDONESIA, PT | F95: HVC | H95: Menunggu konfirmasi kontraktor untuk di pick up, menunggu pembayaran dari alam | J95: Material sudah diterima oleh DCI
A96: 27 | B96: Post Insulator 150 Kv | C96: 8378100 | E96: Sejahtera Mulya Kencana,PT | J96: Invoice Pelunasan
A97: 4 | B97: TRANSPORTASI DAN PENGGESERAN IBT KE -5 GITET KRIAN | C97: 64092000 | D97: Sudah PO | E97: PT KARYASEMBADA CIPTAMANDIRI | F97: HVC | J97: Tanggal 21 Oktober 2022 sudah pelunasan | N97: surat pernyataan sedang produksi dan selesai sesuai SOA
A98: 27 | B98: Maintenance SUTET 500kV Suralaya-Balaraja | C98: 16200000 | D98: Sudah PO | E98: DUTA CAKRAWALA INDONESIA, PT | J98: Invoice pelunasan SOA 224875
A99: 1 | B99: GI 150 kV Bunta | C99: 903268700 | D99: Sudah PO | E99: NSU | F99: STRINGSET DAN HV CONNECTOR | H99: - menunggu PO ke PLP barang sudah ready & menunggu kontraktor mengambil material | J99: Kekurangan insulator sudah dikirim ke surabaya 16/11/2022 sudah sampai ke makasar perkiraan 26/11/2022 - 28/11/2022 | K99: stock & order PLP | L99: - | M99: Ikhbal Pak Dedy | N99: Tanggal Giro 14 November 2022
A100: 12 | B100: PEMBUATAN CAPING SERANDANG ULTG TEGAL | C100: 100000000 | D100: On-progress | E100: PLN UPT PURWOKERTO | F100: Pengadaan dan jasa | H100: Valid kontrak jumat minggu ini | J100: Menunggu pembayaran dari PLN dan BAST tahap 2 diselesaikan di bulan november
A101: 22 | B101: Splice Hunt | C101: 30060000 | D101: Sudah PO | E101: Masera Abadi Utama, PT | J101: Invoice DP SOA 224969(29/11/2022), DP 30% Sudah, Pak dedy mencari forwarder ke ULTG Mojokerto
...

Sheet Sheet2
A2: No | B2: Project Name PT Alam Insektindo | C2: PIC
A3: 1 | B3: 150KV GI LUWUK & TOILI | C3: Fuad
A4: 2 | B4: PAKET 2 BAY TRAFO BANDUNG | C4: Fuad
A5: 3 | B5: GI 150 kV BABAKAN BARU, Indramayu | C5: Priyo
A6: 4 | B6: GI 150 KV KEBUMEN | C6: Priyo
A7: 5 | B7: GI 150 kV Air Raja | C7: Fuad
A8: 6 | B8: TL 150 kV Malimping Bayah | C8: Fuad
A9: 7 | B9: GI 150 kV Tolinggula | C9: Fuad
A10: 8 | B10: GI 150 kV Tawaeli | C10: Fuad
A11: 9 | B11: GI 150 kV Bunta | C11: Fuad
A12: 10 | B12: GIS 150 kV Ancol | C12: Priyo
A13: 11 | B13: GIS 150 kV Ulin | C13: Priyo
A14: 12 | B14: TL 150 kV NEW BALIKPAPAN | C14: Priyo
... A28: 26 | B28: TL 150kV Marunda Bekasi | C28: Priyo
A29: No | B29: Next Project PT Alam Insektindo | C29: PIC
A30: 1 | B30: TL 500 kV Paket 3 Waskita | C30: Ibu Sari
A31: 2 | B31: TL Cibitung | C31: Priyo
A32: 3 | B32: Jatiluhur - Cikampek | C32: Aco
A33: 4 | B33: Rancaekek - Sunyaragi | C33: Aco
A34: 5 | B34: Relokasi 500 kv Cibatu - Cirata | C34: Priyo
A35: 6 | B35: TL Batam Nongsa | C35: Priyo
A36: 7 | B36: Relokasi Tower Moh Toha ( 5 Tower) | C36: Priyo
A37: 8 | B37: Rekonduktoring GSW 55 (UPT Semarang) | C37: Aco & Priyo
A38: 9 | B38: Relokasi Tower di Surabaya | C38: Priyo
A39: 10 | B39: GI Pemantang Siantar SBU | C39: Diki & Priyo
A40: 11 | B40: TL 275 kV-18 Paket | C40: Fuad
A41: 12 | B41: UPT Semarang GI dan TL 150kV 5 Paket | C41: Priyo & Aco
... A63: 34 | B63: Riau GFPP 275 MW IPP Project | C63: Aco & Priyo
A64: No | B64: Project INA | C64: PIC
A65: 1 | B65: Bonomi untuk Muara Enim | C65: Fuad & Diki
A66: 2 | B66: Sediver dan Lagranja | C66: Fuad & Imam
A67: 3 | B67: Pak Tata, PT Pandan Wangi | C67: Fuad
A68: 4 | B68: AC3 DEM | C68: Ibu Sari
A69: 5 | B69: Trans Elektrik | C69: Ibu Sari

Sheet SKYPE
B1: PROJECT ON PROGRESS 2018 - 2019
A3: No | B3: Project Name | C3: Nama Kontraktor | D3: Desc | E3: PLP Promise | F3: Remark Kontraktor | G3: Remak PLP | I3: INSULATOR | J3: Remarks | K3: PIC
A4: 1 | B4: 150KV GI PAMEKASAN STRING | C4: PPWS | D4: STRINGSET | E4: 43504 | F4: NEED REPORT FROM PLP MATERIAL STATUS | G4: Percepatan | J4: STRINGSET Sudah di Gudang, KONEKTOR belum PO (Rabu 8 Mei 19) deadline | K4: Eko
A5: 2 | B5: 150KV GI TJBT KAPASITOR 7 SITE | C5: TDKK | D5: STRINGSET, PROSES PACKING MINGGU INI | E5: 43493 | F5: NEED REPORT PACKING STATUS | G5: Percepatan | J5: Sudah di gudang Marunda | K5: Fuad
A6: 1 | B6: TL 150 kV Caruban Tower 51 - 52 (SOKER) | C6: Matrix | D6: STRINGSET & Isulator | E6: End of Juni 2019 | F6: Approval Drawing | G6: Percepatan | H6: Percepatan | J6: Approval Drawing (10 Mei 19, data semua selesai) | K6: Eko
A7: 2 | B7: TL 150 kV Nganjuk - Caruban Tower 24 - 25 (SOKER) | C7: Matrix | D7: STRINGSET & Isulator | E7: End of Mei 2019 | F7: Approval Drawing | G7: Percepatan | H7: Percepatan | J7: Approval Drawing | K7: Eko
A8: 3 | B8: GI 150 kV PADANG SAMBIAN | C8: Sastra Mas | D8: STRINGSET DAN HV CONNECTOR, PROSES ANTRIAN | E8: 43579 | F8: NEED REPORT PROJECT STATUS, (AO NOT RECEIVED YET) | G8: drawing connector belum diberikan plp | H8: Percepatan | J8: (Konektor) Rabu 8 Mei 19, deadline | K8: Brian
A9: 4 | B9: TL 150 kV Malimping Bayah | C9: K E | D9: Stringset & Ubolt | E9: End of April 2019 | F9: Ada 2 PO Sudah PO | G9: Percepatan | H9: Percepatan | I9: String sudah Oke, Ubolt belum ada update | J9: Hari ini update dari mas fuad (6 mei 19) | K9: Fuad
A10: 5 | B10: 150KV GI LUWUK & TOILI | C10: Amanda | D10: STRINGSET DAN HV CONNECTOR, PROSES ANTRIAN | E10: 43572 | F10: CONTRACTOR REQUEST STRINGSET END OF FEBRUARY | G10: Minta di mundurkan Juni 2019 | H10: 20 Mei 2019, Packing List tanggal 13 Mei 2019 | J10: Material April 2019, Inv DP Sudah terbit belum ada pembayaran (Mundur ke Juni setelah lebaran) | K10: Brian
A11: 6 | B11: GI 150 kV Air Raja | C11: K E | D11: STRINGSET DAN HV CONNECTOR | E11: End Of Juli 2019 | F11: Sudah PO | G11: Promise date | H11: (Clear) Menunggu kabarnya minggu depan | J11: Invoice Pelunasan (Tunggu barang datang) | K11: Fuad
A12: 7 | B12: GI 150 kV BABAKAN BARU TDKK | C12: TDKK | D12: STRINGSET DAN HV CONNECTOR | E12: End of Maret 2019 | F12: Revisi PO dan Revisi Stringset (Drawing) | G12: Minta Drawing ke PLP Urgent | H12: Suspend | J12: Connector tunggu approval, Perlatan | K12: Fuad
A13: 8 | B13: GI 150 KV UNGARAN | C13: Selindo | D13: STRINGSET DAN HV CONNECTOR | E13: End of Maret 2019 | F13: BELUM PO | G13: Minta Drawing ke PLP Urgent | J13: Connector tunggu approval, Perlatan (JULI) | K13: Eko
A14: 9 | B14: TL 150 kV NEW BALIKPAPAN | C14: Waskita Karya | D14: STRINGSET | E14: End Of Juli 2019 | F14: Approval Drawing | G14: Minta Drawing ke PLP Urgent | J14: Approval Drawing (Kop Drawing) | K14: Priyo
A15: 5 | B15: PAKET 2 BAY TRAFO BANDUNG | C15: Amanda | D15: STRINGSET DAN HV CONNECTOR | F15: BELUM PO dari kontraktor | I15: 120 FOG, 700 PCS | J15: 100% PLP | K15: Fuad
A16: 6 | B16: CISUMDAWU PHASE 3 KEDUNG JAYA | C16: Kedung Jaya | D16: STRINGSET | E16: 28 Februari 2019 | F16: BELUM PO | I16: 120 FOG, 840 PCS | J16: Sudah PO, DP Done | K16: Brian
A17: 7 | B17: CISUMDAWU PHASE 4 CMS | C17: CMS | D17: STRINGSET ACSR 450/410 | F17: BELUM PO | J17: Sudah kontrak, Approval OK, PO Masih di tahan | K17: Eko
A18: 8 | B18: GI 150 kV SUMENEP PPWS | C18: PPWS | D18: STRINGSET DAN HV CONNECTOR | E18: End of Maret 2019 | F18: BELUM PO | J18: STRINGSET Sudah di Gudang, KONEKTOR belum PO (Rabu 8 Mei 19) deadline | K18: Eko
A19: 11 | B19: GI 150 KV KEBUMEN | C19: Buana | D19: DISC INSULATOR & PI | E19: End of Maret 2019 | F19: BELUM PO | J19: (JULI), Disc Insulator & Post Insulator | K19: Eko
A20: 14 | B20: GI 150 kV Tolitoli | C20: Fuji SME | D20: STRINGSET DAN HV CONNECTOR | E20: End of Juli - Agustus 2019 | F20: Drawing | G20: PLP Belum kasih gambar konektor dan PO | J20: Prepare Drawing | K20: Fuad
A21: 10 | B21: TL 150 kV Rengat Tembilahan | C21: Waskita Karya | D21: STRINGSET | E21: End of Agustus 2019 | F21: Perubahan Drawing Suspension | G21: Promise date | I21: Juni 2019 | J21: Revisi Gambar (Juni Akhir), Transportasi di takeover oleh divisi | K21: Eko
A22: 16 | B22: GI 150 kV Semen Grobogan | C22: Kencana Alam | D22: STRINGSET DAN HV CONNECTOR | E22: End of Agustus 2019 | F22: Approval Drawing | G22: Penawaran Harga ke PLP | J22: Revisi Gambar (September) | K22: Priyo
A23: 17 | B23: TL 150 kV KM 27 Cikarang Listrindo | C23: DCM | D23: STRINGSET | E23: End of Mei 2019 | F23: Approval Drawing | J23: Approval Drawing di PLN E (Oke), tinggal ke bandung | K23: Eko
B24: TL 150 kV KM 27 Cikarang Listrindo | C24: ALHAS | D24: STRINGSET | F24: Approval Drawing | J24: Approval Drawing di PLN E (Oke), tinggal ke bandung | K24: Eko
A25: 18 | B25: TL 150 kV Krian - Manyar (KLBM) | C25: Matrix | D25: STRINGSET & Isulator | E25: End of Mei 2019 | F25: Approval Drawing | J25: Approval Drawing Oke | K25: Eko
A26: 21 | B26: GI 150 kV Bangkir | C26: NSU | D26: STRINGSET DAN HV CONNECTOR | E26: End of Juni 2019 | F26: Approval Drawing | G26: Sudah terima Penawaran Harga dari PLP | J26: Tunggu PO Kontraktor ke Alam | K26: Priyo
A27: 22 | B27: GI 150 kV Tolinggula | C27: NSU | D27: STRINGSET DAN HV CONNECTOR | E27: End of Juni 2019 | F27: Approval Drawing | G27: Sudah terima Penawaran Harga dari PLP | H27: 12 Minggu | J27: Tunggu PO Kontraktor ke Alam | K27: Priyo
A28: 23 | B28: GI 150 kV Tawaeli | C28: NSU | D28: STRINGSET DAN HV CONNECTOR | E28: End of Juni 2019 | F28: Approval Drawing | J28: Tunggu PO Kontraktor ke Alam | K28: Priyo
A29: 24 | B29: GI 150 kV Bunta | C29: NSU | D29: STRINGSET DAN HV CONNECTOR | E29: End of Juni 2019 | F29: Approval Drawing | J29: Tunggu PO Kontraktor ke Alam | K29: Priyo
A30: 25 | B30: TL 500 kV Paket 1 dan 2 Additional | C30: Waskita Karya | D30: STRINGSET | E30: End of 12 April 2019 | F30: Approval Drawing | J30: Kirim Ke Pekanbaru & Jambi (BackUp Uki untuk Inv) | K30: Brian
A31: 26 | B31: GI 150 kV SUNYARAGI | C31: MPT | D31: DISC INSULATOR | E31: End of Desember 2019 | F31: Approval Drawing | I31: 120 FOG, 1250 PCS | J31: Tunggu PO Kontraktor ke Alam | K31: Priyo
A32: 27 | B32: GI 150 kV SEMEN JAWA | C32: MPT | D32: STRINGSET DAN HV CONNECTOR | E32: End of Desember 2019 | F32: Approval Drawing | G32: Tunggu penawaran dari PLP | J32: Tunggu PO Kontraktor ke Alam | K32: Priyo
A33: 28 | B33: GIS 150 kV Jatake | C33: Lumintu | D33: STRINGSET DAN HV CONNECTOR | E33: Belum STL | F33: Approval Drawing | J33: Approval Drawing | K33: Priyo
A34: 29 | B34: GI 150 kV Ancol | C34: Lumintu | D34: STRINGSET DAN HV CONNECTOR | E34: Belum STL | F34: Approval Drawing | J34: Approval Drawing | K34: Eko
A35: 30 | B35: GIS 150 kV Ulin | C35: Distraco | D35: STRINGSET DAN HV CONNECTOR | E35: End of April 2019 | F35: Approval Drawing | J35: Approval Drawing | K35: Eko
A36: 31 | B36: GI 150 KV Balong Bendo | C36: GTS | D36: STRINGSET DAN HV CONNECTOR | E36: End of September 2019 | F36: Approval Drawing | G36: Menunggu Penawaran Harga dari PLP | J36: Approval Drawing | K36: Fuad
A37: 33 | B37: TL 150 kV - KCIC (Kereta Api Cepat) | C37: CMS | D37: STRINGSET | E37: End of Agustus 2019 | F37: Approval Drawing | G37: PO Hari ini by mas fuad ke PLP (6 Mei 19) | J37: Approval Drawing (Kop Drawing) | K37: Eko
A38: 34 | B38: TL 150 kV - KCIC (Kereta Api Cepat) | C38: DCM | D38: STRINGSET | E38: End of Agustus 2019 | F38: Approval Drawing | G38: PO Hari ini by mas fuad ke PLP (6 Mei 19) | J38: Approval Drawing (Kop Drawing) | K38: Eko
A39: 35 | B39: GI 150 kV Cianjur | C39: ABB - TDKK | D39: STRINGSET DAN HV CONNECTOR | E39: End Of Oktober 2019 | F39: Approval Drawing | J39: Approval Drawing (Kop Drawing) | K39: Eko
